Workbook

Sheet BASE DE DATOS DE PRODUCTOS
A1: LISTA DE PRODUCTOS
A5: CODIGO | B5: NOMBRE DEL PRODUCTO | C5: CATEGORIA | D5: OBSERVACIÓN
A6: A001 | B6: DETERGENTE BIO AZUL DE 5 LITROS | C6: LAVANDERIA
A7: A002 | B7: DETERGENTE BIO VERDE DE 5 LITROS | C7: LAVANDERIA
A8: A003 | B8: DETERGENTE MORADO CON SUAVIZANTE DE 5 LITROS | C8: LAVANDERIA
A9: A004 | B9: DETERGENTE BLANCO CON SUAVIZANTE DE 5 LITROS | C9: LAVANDERIA
A10: A005 | B10: DETERGENTE CELESTE CON SUAVIZANTE DE 5 LITROS | C10: LAVANDERIA
A11: A006 | B11: DETERGENTE NARANJO CON SUAVIZANTE DE 5 LITROS | C11: LAVANDERIA
A12: A007 | B12: DETERGENTE ROSADO CON SUAVIZANTE DE 5 LITROS | C12: LAVANDERIA
A13: A008 | B13: DETERGENTE PREMIUM AROMA OMO DE 3 LITROS (PACK DE 4 UNID) | C13: LAVANDERIA
A14: A009 | B14: DETERGENTE DE BEBÉ 3 LITROS | C14: LAVANDERIA
A15: A010 | B15: DETERGENTE OMO PARA DILUIR 3 LITROS | C15: LAVANDERIA
A16: A011 | B16: DETERGENTE OMO DE 400 ML | C16: LAVANDERIA
A17: A012 | B17: DETERGENTE OMO LIQUIDO BIDÓN 3 LITROS | C17: LAVANDERIA | D17: ME FALTA COMPRAR
A18: A013 | B18: DETERGENTE BIO KLINNING AZUL | C18: LAVANDERIA | D18: ME FALTA COMPRAR
A19: A014 | B19: DETERGENTE BIO KLINNING VERDE | C19: LAVANDERIA | D19: ME FALTA COMPRAR
A20: A015 | B20: DETERGENTE SOFT LIQUIDO BIDÓN DE 3 LITROS | C20: LAVANDERIA | D20: ME FALTA COMPRAR
A21: A016 | B21: DETERGENTE EN POLVO QUITA MANCHA ROSADO | C21: LAVANDERIA
A22: A017 | B22: DETERGENTE EN POLVO QUITA MANCHA MORADO | C22: LAVANDERIA
A23: A018 | B23: DETERGENTE EN POLVO VIRGINIA | C23: LAVANDERIA
A24: A019 | B24: CLORO ROPA BLANCA SPUM DE 1 LITRO | C24: LAVANDERIA
A25: A020 | B25: CLORO ROPA A COLOR SPUM DE 1 LITRO | C25: LAVANDERIA
A26: A021 | B26: VANISH BLANCO | C26: LAVANDERIA | D26: ME FALTA COMPRAR
A27: A022 | B27: VANISH ROSADO | C27: LAVANDERIA | D27: ME FALTA COMPRAR
A28: A023 | B28: CLORO CONCENTRADO DE 5 LITROS | C28: DESINFECCIÓN
A29: A024 | B29: CLORINDA DE 1 LITRO | C29: DESINFECCIÓN | D29: ME FALTA COMPRAR
A30: A025 | B30: CLORO GEL CLOROX | C30: DESINFECCIÓN | D30: ME FALTA COMPRAR
A31: A026 | B31: CLORO IGENIX LIQUIDO | C31: DESINFECCIÓN
A32: A027 | B32: CLORINDA CLORO GEL | C32: DESINFECCIÓN
A33: A028 | B33: CLORINDA CLORO GEL EXCEL MORADO | C33: DESINFECCIÓN
A34: A029 | B34: CLORINDA CLORO GEL EXCEL AMARILLO | C34: DESINFECCIÓN
A35: A030 | B35: ANTIGRASA SPUM DE 2 LITROS | C35: COCINA
A36: A031 | B36: ANTIGRASA SPUM DE 500 ML | C36: COCINA
A37: A032 | B37: SACASARRO SPUM DE 2 LITROS | C37: COCINA
A38: A033 | B38: SACASARRO SPUM DE 500 ML | C38: COCINA
A39: A034 | B39: LAVALOSA SPUM DE 1 LITRO | C39: COCINA
A40: A035 | B40: LAVALOSA SPUM DE 2 LITROS | C40: COCINA
A41: A036 | B41: LAVALOSA SPUM DE 5 LITROS | C41: COCINA
A42: A037 | B42: LAVALOSA QUIX | C42: COCINA | D42: ME FALTA COMPRAR
A43: A038 | B43: CIF | C43: COCINA
A44: A039 | B44: LUSTRA MUEBLES | C44: COCINA
A45: A040 | B45: LIMPIA VIDRIOS DE 500CC | C45: COCINA
A46: A041 | B46: LIMPIA PISOS FLOTANTE | C46: COCINA
A47: A042 | B47: VIRUTILLA | C47: COCINA
A48: A043 | B48: LIMPIA PISOS SPUM COLOR ROJO | C48: SUPERFICIE
A49: A044 | B49: LIMPIA PISOS SPUM COLOR AZUL | C49: SUPERFICIE
A50: A045 | B50: LIMPIA PISOS BRILLEX AMARILLO | C50: SUPERFICIE
A51: A046 | B51: LIMPIA PISOS AROMAX AZUL | C51: SUPERFICIE
A52: A047 | B52: LIMPIA PISOS AROMAX ROSADO | C52: SUPERFICIE
A53: A048 | B53: LIMPIA PISOS AROMAX MORADO | C53: SUPERFICIE
A54: A049 | B54: LIMPIA PISOS POETT ROSADO | C54: SUPERFICIE
... A76: A071 | B76: JABON LIQUIDO COLOR CELESTE | C76: HIGIENE PERSONAL
A77: A072 | B77: JABON LIQUIDO DOVE | C77: HIGIENE PERSONAL | D77: ME FALTA COMPRAR
A78: A073 | B78: JABON EN BARRA DOVE | C78: HIGIENE PERSONAL
A79: A074 | B79: PAPEL HIGIENICO SCOTT 50 MTS | C79: HIGIENE PERSONAL
A80: A075 | B80: PAPEL HIGIENICO ECONOMICO 23 MTS | C80: HIGIENE PERSONAL
A81: A076 | B81: PAPEL HIGIENICO NOBLE 23 MTS | C81: HIGIENE PERSONAL
A82: A077 | B82: SERVILLETAS SUAN | C82: HIGIENE PERSONAL
A83: A078 | B83: TOALLA NOVA ABOLENGO | C83: HIGIENE PERSONAL
A84: A079 | B84: TOALLA NOVA SUAN | C84: HIGIENE PERSONAL
A85: A080 | B85: TOALLA NOVA | C85: HIGIENE PERSONAL
A86: A081 | B86: TOALLA NOVA 70 MTS | C86: HIGIENE PERSONAL
A87: A082 | B87: CEPILLO DE DIENTES | C87: HIGIENE PERSONAL
A88: A083 | B88: PASTA DE DIENTES AQUAFRESH | C88: HIGIENE PERSONAL
A89: A084 | B89: PASTA DE DIENTES COLGATE | C89: HIGIENE PERSONAL
... A124: A119 | B124: DETERGENTE PREMIUM AROMA OMO DE 3 LITROS (1 UNID) | C124: LAVANDERIA

Sheet Hoja1
C3: detalle | E3: stock | F3: compra
C4: detergente saca mancha lavanda | E4: 5 | F4: 6
C5: detergente saca mancha floral | E5: 6 | F5: 6
C6: detergente virginia | E6: 6 | F6: 6
C7: omo para diluir | E7: 14 | F7: 24
C8: omo liquido 400ml | E8: 7 | F8: 12
C9: shampoo familand granada | E9: 3 | F9: 6
C10: acondicionador familand | E10: 4 | F10: 6
C11: shampoo dove | E11: 5 | F11: 6
C12: acondicionador dove | E12: 5 | F12: 6
C13: shampoo ballerina | E13: 5
C14: acondicionador ballerina | E14: 8
C15: spum de bebe | E15: 5 | F15: 4
C16: detergente bio | E16: 14 | F16: 12
C17: cloro gel limon | E17: 5 | F17: 5
C18: cloro gel lavanda | E18: 5 | F18: 5
C19: trapero deseshable limon
C20: trapero deseshable lavanda
C21: desodorante ambiental poett

Sheet PARAMETROS
A5: CATEGORIAS
A6: LAVANDERIA
A7: DESINFECCIÓN
A8: COCINA
A9: SUPERFICIE
A10: AMBIENTADORES
A11: HIGIENE PERSONAL
A12: ACCESORIOS DE LIMPIEZA
A13: PLAGAS
A14: RESIDUOS

Sheet INVENTARIO
A1: INVENTARIO
J4: TOTAL INVENTARIO
J5: =SUBTOTAL(9,INVENTARIO[[#All],[VALOR DEL INVENTARIO]]) -> 1059018
A6: CODIGO | B6: NOMBRE DEL PRODUCTO | C6: CATEGORIA | D6: COMPRAS | E6: VENTAS | F6: STOCK | G6: COSTO UNITARIO | H6: PRECIO DE VENTA | I6: UTILIDAD POR PRODUCTO | J6: VALOR DEL INVENTARIO | K6: GANANCIA TOTAL DE CADA PRODFUCTO
A7: A001 | B7: =IFERROR(VLOOKUP(INVENTARIO[[#This Row],[CODIGO]],BASEDEDATOS[],2,FALSE),"NO EXISTE") -> DETERGENTE BIO AZUL DE 5 LITROS | C7: =IFERROR(VLOOKUP(INVENTARIO[[#This Row],[CODIGO]],BASEDEDATOS[],3,FALSE),"NO EXISTE") -> LAVANDERIA | D7: 150 | E7: 11 | F7: =INVENTARIO[[#This Row],[COMPRAS]]-INVENTARIO[[#This Row],[VENTAS]] -> 139 | G7: 920 | H7: 1800 | I7: =INVENTARIO[[#This Row],[PRECIO DE VENTA]]-INVENTARIO[[#This Row],[COSTO UNITARIO]] -> 880 | J7: =INVENTARIO[[#This Row],[COSTO UNITARIO]]*INVENTARIO[[#This Row],[STOCK]] -> 127880 | K7: =+INVENTARIO[[#This Row],[VENTAS]]*INVENTARIO[[#This Row],[UTILIDAD POR PRODUCTO]] -> 9680
A8: A002 | B8: =IFERROR(VLOOKUP(INVENTARIO[[#This Row],[CODIGO]],BASEDEDATOS[],2,FALSE),"NO EXISTE") -> DETERGENTE BIO VERDE DE 5 LITROS | C8: =IFERROR(VLOOKUP(INVENTARIO[[#This Row],[CODIGO]],BASEDEDATOS[],3,FALSE),"NO EXISTE") -> LAVANDERIA | D8: 50 | E8: 8 | F8: =INVENTARIO[[#This Row],[COMPRAS]]-INVENTARIO[[#This Row],[VENTAS]] -> 42 | G8: 920 | H8: 1800 | I8: =INVENTARIO[[#This Row],[PRECIO DE VENTA]]-INVENTARIO[[#This Row],[COSTO UNITARIO]] -> 880 | J8: =INVENTARIO[[#This Row],[COSTO UNITARIO]]*INVENTARIO[[#This Row],[STOCK]] -> 38640 | K8: =+INVENTARIO[[#This Row],[VENTAS]]*INVENTARIO[[#This Row],[UTILIDAD POR PRODUCTO]] -> 7040
A9: A003 | B9: =IFERROR(VLOOKUP(INVENTARIO[[#This Row],[CODIGO]],BASEDEDATOS[],2,FALSE),"NO EXISTE") -> DETERGENTE MORADO CON SUAVIZANTE DE 5 LITROS | C9: =IFERROR(VLOOKUP(INVENTARIO[[#This Row],[CODIGO]],BASEDEDATOS[],3,FALSE),"NO EXISTE") -> LAVANDERIA | D9: 10 | E9: 4 | F9: =INVENTARIO[[#This Row],[COMPRAS]]-INVENTARIO[[#This Row],[VENTAS]] -> 6 | G9: 1490 | H9: 2500 | I9: =INVENTARIO[[#This Row],[PRECIO DE VENTA]]-INVENTARIO[[#This Row],[COSTO UNITARIO]] -> 1010 | J9: =INVENTARIO[[#This Row],[COSTO UNITARIO]]*INVENTARIO[[#This Row],[STOCK]] -> 8940 | K9: =+INVENTARIO[[#This Row],[VENTAS]]*INVENTARIO[[#This Row],[UTILIDAD POR PRODUCTO]] -> 4040
A10: A004 | B10: =IFERROR(VLOOKUP(INVENTARIO[[#This Row],[CODIGO]],BASEDEDATOS[],2,FALSE),"NO EXISTE") -> DETERGENTE BLANCO CON SUAVIZANTE DE 5 LITROS | C10: =IFERROR(VLOOKUP(INVENTARIO[[#This Row],[CODIGO]],BASEDEDATOS[],3,FALSE),"NO EXISTE") -> LAVANDERIA | D10: 60 | E10: 2 | F10: =INVENTARIO[[#This Row],[COMPRAS]]-INVENTARIO[[#This Row],[VENTAS]] -> 58 | G10: 1490 | H10: 2500 | I10: =INVENTARIO[[#This Row],[PRECIO DE VENTA]]-INVENTARIO[[#This Row],[COSTO UNITARIO]] -> 1010 | J10: =INVENTARIO[[#This Row],[COSTO UNITARIO]]*INVENTARIO[[#This Row],[STOCK]] -> 86420 | K10: =+INVENTARIO[[#This Row],[VENTAS]]*INVENTARIO[[#This Row],[UTILIDAD POR PRODUCTO]] -> 2020
A11: A005 | B11: =IFERROR(VLOOKUP(INVENTARIO[[#This Row],[CODIGO]],BASEDEDATOS[],2,FALSE),"NO EXISTE") -> DETERGENTE CELESTE CON SUAVIZANTE DE 5 LITROS | C11: =IFERROR(VLOOKUP(INVENTARIO[[#This Row],[CODIGO]],BASEDEDATOS[],3,FALSE),"NO EXISTE") -> LAVANDERIA | D11: 60 | E11: 9 | F11: =INVENTARIO[[#This Row],[COMPRAS]]-INVENTARIO[[#This Row],[VENTAS]] -> 51 | G11: 1490 | H11: 2500 | I11: =INVENTARIO[[#This Row],[PRECIO DE VENTA]]-INVENTARIO[[#This Row],[COSTO UNITARIO]] -> 1010 | J11: =INVENTARIO[[#This Row],[COSTO UNITARIO]]*INVENTARIO[[#This Row],[STOCK]] -> 75990 | K11: =+INVENTARIO[[#This Row],[VENTAS]]*INVENTARIO[[#This Row],[UTILIDAD POR PRODUCTO]] -> 9090
A12: A006 | B12: =IFERROR(VLOOKUP(INVENTARIO[[#This Row],[CODIGO]],BASEDEDATOS[],2,FALSE),"NO EXISTE") -> DETERGENTE NARANJO CON SUAVIZANTE DE 5 LITROS | C12: =IFERROR(VLOOKUP(INVENTARIO[[#This Row],[CODIGO]],BASEDEDATOS[],3,FALSE),"NO EXISTE") -> LAVANDERIA | D12: 30 | E12: 2 | F12: =INVENTARIO[[#This Row],[COMPRAS]]-INVENTARIO[[#This Row],[VENTAS]] -> 28 | G12: 1490 | H12: 2500 | I12: =INVENTARIO[[#This Row],[PRECIO DE VENTA]]-INVENTARIO[[#This Row],[COSTO UNITARIO]] -> 1010 | J12: =INVENTARIO[[#This Row],[COSTO UNITARIO]]*INVENTARIO[[#This Row],[STOCK]] -> 41720 | K12: =+INVENTARIO[[#This Row],[VENTAS]]*INVENTARIO[[#This Row],[UTILIDAD POR PRODUCTO]] -> 2020
A13: A007 | B13: =IFERROR(VLOOKUP(INVENTARIO[[#This Row],[CODIGO]],BASEDEDATOS[],2,FALSE),"NO EXISTE") -> DETERGENTE ROSADO CON SUAVIZANTE DE 5 LITROS | C13: =IFERROR(VLOOKUP(INVENTARIO[[#This Row],[CODIGO]],BASEDEDATOS[],3,FALSE),"NO EXISTE") -> LAVANDERIA | D13: 40 | E13: 2 | F13: =INVENTARIO[[#This Row],[COMPRAS]]-INVENTARIO[[#This Row],[VENTAS]] -> 38 | G13: 1490 | H13: 2500 | I13: =INVENTARIO[[#This Row],[PRECIO DE VENTA]]-INVENTARIO[[#This Row],[COSTO UNITARIO]] -> 1010 | J13: =INVENTARIO[[#This Row],[COSTO UNITARIO]]*INVENTARIO[[#This Row],[STOCK]] -> 56620 | K13: =+INVENTARIO[[#This Row],[VENTAS]]*INVENTARIO[[#This Row],[UTILIDAD POR PRODUCTO]] -> 2020
A14: A008 | B14: =IFERROR(VLOOKUP(INVENTARIO[[#This Row],[CODIGO]],BASEDEDATOS[],2,FALSE),"NO EXISTE") -> DETERGENTE PREMIUM AROMA OMO DE 3 LITROS (PACK DE 4 UNID) | C14: =IFERROR(VLOOKUP(INVENTARIO[[#This Row],[CODIGO]],BASEDEDATOS[],3,FALSE),"NO EXISTE") -> LAVANDERIA | D14: 16 | E14: 16 | F14: =INVENTARIO[[#This Row],[COMPRAS]]-INVENTARIO[[#This Row],[VENTAS]] -> 0 | G14: 1350 | H14: 3000 | I14: =INVENTARIO[[#This Row],[PRECIO DE VENTA]]-INVENTARIO[[#This Row],[COSTO UNITARIO]] -> 1650 | J14: =INVENTARIO[[#This Row],[COSTO UNITARIO]]*INVENTARIO[[#This Row],[STOCK]] -> 0 | K14: =+INVENTARIO[[#This Row],[VENTAS]]*INVENTARIO[[#This Row],[UTILIDAD POR PRODUCTO]] -> 26400
A15: A009 | B15: =IFERROR(VLOOKUP(INVENTARIO[[#This Row],[CODIGO]],BASEDEDATOS[],2,FALSE),"NO EXISTE") -> DETERGENTE DE BEBÉ 3 LITROS | C15: =IFERROR(VLOOKUP(INVENTARIO[[#This Row],[CODIGO]],BASEDEDATOS[],3,FALSE),"NO EXISTE") -> LAVANDERIA | D15: 5 | E15: 2 | F15: =INVENTARIO[[#This Row],[COMPRAS]]-INVENTARIO[[#This Row],[VENTAS]] -> 3 | G15: 2450 | H15: 4000 | I15: =INVENTARIO[[#This Row],[PRECIO DE VENTA]]-INVENTARIO[[#This Row],[COSTO UNITARIO]] -> 1550 | J15: =INVENTARIO[[#This Row],[COSTO UNITARIO]]*INVENTARIO[[#This Row],[STOCK]] -> 7350 | K15: =+INVENTARIO[[#This Row],[VENTAS]]*INVENTARIO[[#This Row],[UTILIDAD POR PRODUCTO]] -> 3100
A16: A010 | B16: =IFERROR(VLOOKUP(INVENTARIO[[#This Row],[CODIGO]],BASEDEDATOS[],2,FALSE),"NO EXISTE") -> DETERGENTE OMO PARA DILUIR 3 LITROS | C16: =IFERROR(VLOOKUP(INVENTARIO[[#This Row],[CODIGO]],BASEDEDATOS[],3,FALSE),"NO EXISTE") -> LAVANDERIA | D16: 24 | E16: 11 | F16: =INVENTARIO[[#This Row],[COMPRAS]]-INVENTARIO[[#This Row],[VENTAS]] -> 13 | G16: 3490 | H16: 4500 | I16: =INVENTARIO[[#This Row],[PRECIO DE VENTA]]-INVENTARIO[[#This Row],[COSTO UNITARIO]] -> 1010 | J16: =INVENTARIO[[#This Row],[COSTO UNITARIO]]*INVENTARIO[[#This Row],[STOCK]] -> 45370 | K16: =+INVENTARIO[[#This Row],[VENTAS]]*INVENTARIO[[#This Row],[UTILIDAD POR PRODUCTO]] -> 11110
A17: A011 | B17: =IFERROR(VLOOKUP(INVENTARIO[[#This Row],[CODIGO]],BASEDEDATOS[],2,FALSE),"NO EXISTE") -> DETERGENTE OMO DE 400 ML | C17: =IFERROR(VLOOKUP(INVENTARIO[[#This Row],[CODIGO]],BASEDEDATOS[],3,FALSE),"NO EXISTE") -> LAVANDERIA | D17: 15 | E17: 3 | F17: =INVENTARIO[[#This Row],[COMPRAS]]-INVENTARIO[[#This Row],[VENTAS]] -> 12 | G17: 690 | H17: 1000 | I17: =INVENTARIO[[#This Row],[PRECIO DE VENTA]]-INVENTARIO[[#This Row],[COSTO UNITARIO]] -> 310 | J17: =INVENTARIO[[#This Row],[COSTO UNITARIO]]*INVENTARIO[[#This Row],[STOCK]] -> 8280 | K17: =+INVENTARIO[[#This Row],[VENTAS]]*INVENTARIO[[#This Row],[UTILIDAD POR PRODUCTO]] -> 930
A18: A012 | B18: =IFERROR(VLOOKUP(INVENTARIO[[#This Row],[CODIGO]],BASEDEDATOS[],2,FALSE),"NO EXISTE") -> DETERGENTE OMO LIQUIDO BIDÓN 3 LITROS | C18: =IFERROR(VLOOKUP(INVENTARIO[[#This Row],[CODIGO]],BASEDEDATOS[],3,FALSE),"NO EXISTE") -> LAVANDERIA | D18: 0 | E18: {=SUM(SUMIF(VENTAS[CODIGO],INVENTARIO!A17:A20,VENTAS[CANTIDAD]))} -> 0 | F18: =INVENTARIO[[#This Row],[COMPRAS]]-INVENTARIO[[#This Row],[VENTAS]] -> 0 | G18: 0 | H18: 0 | I18: =INVENTARIO[[#This Row],[PRECIO DE VENTA]]-INVENTARIO[[#This Row],[COSTO UNITARIO]] -> 0 | J18: =INVENTARIO[[#This Row],[COSTO UNITARIO]]*INVENTARIO[[#This Row],[STOCK]] -> 0 | K18: =+INVENTARIO[[#This Row],[VENTAS]]*INVENTARIO[[#This Row],[UTILIDAD POR PRODUCTO]] -> 0
A19: A013 | B19: =IFERROR(VLOOKUP(INVENTARIO[[#This Row],[CODIGO]],BASEDEDATOS[],2,FALSE),"NO EXISTE") -> DETERGENTE BIO KLINNING AZUL | C19: =IFERROR(VLOOKUP(INVENTARIO[[#This Row],[CODIGO]],BASEDEDATOS[],3,FALSE),"NO EXISTE") -> LAVANDERIA | D19: 16 | E19: 0 | F19: =INVENTARIO[[#This Row],[COMPRAS]]-INVENTARIO[[#This Row],[VENTAS]] -> 16 | G19: 950 | H19: 0 | I19: =INVENTARIO[[#This Row],[PRECIO DE VENTA]]-INVENTARIO[[#This Row],[COSTO UNITARIO]] -> -950 | J19: =INVENTARIO[[#This Row],[COSTO UNITARIO]]*INVENTARIO[[#This Row],[STOCK]] -> 15200 | K19: =+INVENTARIO[[#This Row],[VENTAS]]*INVENTARIO[[#This Row],[UTILIDAD POR PRODUCTO]] -> 0
A20: A014 | B20: =IFERROR(VLOOKUP(INVENTARIO[[#This Row],[CODIGO]],BASEDEDATOS[],2,FALSE),"NO EXISTE") -> DETERGENTE BIO KLINNING VERDE | C20: =IFERROR(VLOOKUP(INVENTARIO[[#This Row],[CODIGO]],BASEDEDATOS[],3,FALSE),"NO EXISTE") -> LAVANDERIA | D20: 16 | E20: {=SUM(SUMIF(VENTAS[CODIGO],INVENTARIO!A19:A22,VENTAS[CANTIDAD]))} -> 0 | F20: =INVENTARIO[[#This Row],[COMPRAS]]-INVENTARIO[[#This Row],[VENTAS]] -> 16 | G20: 950 | H20: 0 | I20: =INVENTARIO[[#This Row],[PRECIO DE VENTA]]-INVENTARIO[[#This Row],[COSTO UNITARIO]] -> -950 | J20: =INVENTARIO[[#This Row],[COSTO UNITARIO]]*INVENTARIO[[#This Row],[STOCK]] -> 15200 | K20: =+INVENTARIO[[#This Row],[VENTAS]]*INVENTARIO[[#This Row],[UTILIDAD POR PRODUCTO]] -> 0
A21: A015 | B21: =IFERROR(VLOOKUP(INVENTARIO[[#This Row],[CODIGO]],BASEDEDATOS[],2,FALSE),"NO EXISTE") -> DETERGENTE SOFT LIQUIDO BIDÓN DE 3 LITROS | C21: =IFERROR(VLOOKUP(INVENTARIO[[#This Row],[CODIGO]],BASEDEDATOS[],3,FALSE),"NO EXISTE") -> LAVANDERIA | D21: 0 | E21: {=SUM(SUMIF(VENTAS[CODIGO],INVENTARIO!A20:A23,VENTAS[CANTIDAD]))} -> 0 | F21: =INVENTARIO[[#This Row],[COMPRAS]]-INVENTARIO[[#This Row],[VENTAS]] -> 0 | G21: 0 | H21: 0 | I21: =INVENTARIO[[#This Row],[PRECIO DE VENTA]]-INVENTARIO[[#This Row],[COSTO UNITARIO]] -> 0 | J21: =INVENTARIO[[#This Row],[COSTO UNITARIO]]*INVENTARIO[[#This Row],[STOCK]] -> 0 | K21: =+INVENTARIO[[#This Row],[VENTAS]]*INVENTARIO[[#This Row],[UTILIDAD POR PRODUCTO]] -> 0
A22: A016 | B22: =IFERROR(VLOOKUP(INVENTARIO[[#This Row],[CODIGO]],BASEDEDATOS[],2,FALSE),"NO EXISTE") -> DETERGENTE EN POLVO QUITA MANCHA ROSADO | C22: =IFERROR(VLOOKUP(INVENTARIO[[#This Row],[CODIGO]],BASEDEDATOS[],3,FALSE),"NO EXISTE") -> LAVANDERIA | D22: 6 | E22: 2 | F22: =INVENTARIO[[#This Row],[COMPRAS]]-INVENTARIO[[#This Row],[VENTAS]] -> 4 | G22: 490 | H22: 1000 | I22: =INVENTARIO[[#This Row],[PRECIO DE VENTA]]-INVENTARIO[[#This Row],[COSTO UNITARIO]] -> 510 | J22: =INVENTARIO[[#This Row],[COSTO UNITARIO]]*INVENTARIO[[#This Row],[STOCK]] -> 1960 | K22: =+INVENTARIO[[#This Row],[VENTAS]]*INVENTARIO[[#This Row],[UTILIDAD POR PRODUCTO]] -> 1020
A23: A017 | B23: =IFERROR(VLOOKUP(INVENTARIO[[#This Row],[CODIGO]],BASEDEDATOS[],2,FALSE),"NO EXISTE") -> DETERGENTE EN POLVO QUITA MANCHA MORADO | C23: =IFERROR(VLOOKUP(INVENTARIO[[#This Row],[CODIGO]],BASEDEDATOS[],3,FALSE),"NO EXISTE") -> LAVANDERIA | D23: 6 | E23: 1 | F23: =INVENTARIO[[#This Row],[COMPRAS]]-INVENTARIO[[#This Row],[VENTAS]] -> 5 | G23: 490 | H23: 1000 | I23: =INVENTARIO[[#This Row],[PRECIO DE VENTA]]-INVENTARIO[[#This Row],[COSTO UNITARIO]] -> 510 | J23: =INVENTARIO[[#This Row],[COSTO UNITARIO]]*INVENTARIO[[#This Row],[STOCK]] -> 2450 | K23: =+INVENTARIO[[#This Row],[VENTAS]]*INVENTARIO[[#This Row],[UTILIDAD POR PRODUCTO]] -> 510
A24: A018 | B24: =IFERROR(VLOOKUP(INVENTARIO[[#This Row],[CODIGO]],BASEDEDATOS[],2,FALSE),"NO EXISTE") -> DETERGENTE EN POLVO VIRGINIA | C24: =IFERROR(VLOOKUP(INVENTARIO[[#This Row],[CODIGO]],BASEDEDATOS[],3,FALSE),"NO EXISTE") -> LAVANDERIA | D24: 18 | E24: 0 | F24: =INVENTARIO[[#This Row],[COMPRAS]]-INVENTARIO[[#This Row],[VENTAS]] -> 18 | G24: 890 | H24: 2000 | I24: =INVENTARIO[[#This Row],[PRECIO DE VENTA]]-INVENTARIO[[#This Row],[COSTO UNITARIO]] -> 1110 | J24: =INVENTARIO[[#This Row],[COSTO UNITARIO]]*INVENTARIO[[#This Row],[STOCK]] -> 16020 | K24: =+INVENTARIO[[#This Row],[VENTAS]]*INVENTARIO[[#This Row],[UTILIDAD POR PRODUCTO]] -> 0
A25: A019 | B25: =IFERROR(VLOOKUP(INVENTARIO[[#This Row],[CODIGO]],BASEDEDATOS[],2,FALSE),"NO EXISTE") -> CLORO ROPA BLANCA SPUM DE 1 LITRO | C25: =IFERROR(VLOOKUP(INVENTARIO[[#This Row],[CODIGO]],BASEDEDATOS[],3,FALSE),"NO EXISTE") -> LAVANDERIA | D25: 12 | E25: 4 | F25: =INVENTARIO[[#This Row],[COMPRAS]]-INVENTARIO[[#This Row],[VENTAS]] -> 8 | G25: 733 | H25: 1500 | I25: =INVENTARIO[[#This Row],[PRECIO DE VENTA]]-INVENTARIO[[#This Row],[COSTO UNITARIO]] -> 767 | J25: =INVENTARIO[[#This Row],[COSTO UNITARIO]]*INVENTARIO[[#This Row],[STOCK]] -> 5864 | K25: =+INVENTARIO[[#This Row],[VENTAS]]*INVENTARIO[[#This Row],[UTILIDAD POR PRODUCTO]] -> 3068
A26: A020 | B26: =IFERROR(VLOOKUP(INVENTARIO[[#This Row],[CODIGO]],BASEDEDATOS[],2,FALSE),"NO EXISTE") -> CLORO ROPA A COLOR SPUM DE 1 LITRO | C26: =IFERROR(VLOOKUP(INVENTARIO[[#This Row],[CODIGO]],BASEDEDATOS[],3,FALSE),"NO EXISTE") -> LAVANDERIA | D26: 24 | E26: 5 | F26: =INVENTARIO[[#This Row],[COMPRAS]]-INVENTARIO[[#This Row],[VENTAS]] -> 19 | G26: 666 | H26: 1500 | I26: =INVENTARIO[[#This Row],[PRECIO DE VENTA]]-INVENTARIO[[#This Row],[COSTO UNITARIO]] -> 834 | J26: =INVENTARIO[[#This Row],[COSTO UNITARIO]]*INVENTARIO[[#This Row],[STOCK]] -> 12654 | K26: =+INVENTARIO[[#This Row],[VENTAS]]*INVENTARIO[[#This Row],[UTILIDAD POR PRODUCTO]] -> 4170
A27: A021 | B27: =IFERROR(VLOOKUP(INVENTARIO[[#This Row],[CODIGO]],BASEDEDATOS[],2,FALSE),"NO EXISTE") -> VANISH BLANCO | C27: =IFERROR(VLOOKUP(INVENTARIO[[#This Row],[CODIGO]],BASEDEDATOS[],3,FALSE),"NO EXISTE") -> LAVANDERIA | D27: 12 | E27: 10 | F27: =INVENTARIO[[#This Row],[COMPRAS]]-INVENTARIO[[#This Row],[VENTAS]] -> 2 | G27: 303 | H27: 650 | I27: =INVENTARIO[[#This Row],[PRECIO DE VENTA]]-INVENTARIO[[#This Row],[COSTO UNITARIO]] -> 347 | J27: =INVENTARIO[[#This Row],[COSTO UNITARIO]]*INVENTARIO[[#This Row],[STOCK]] -> 606 | K27: =+INVENTARIO[[#This Row],[VENTAS]]*INVENTARIO[[#This Row],[UTILIDAD POR PRODUCTO]] -> 3470
A28: A022 | B28: =IFERROR(VLOOKUP(INVENTARIO[[#This Row],[CODIGO]],BASEDEDATOS[],2,FALSE),"NO EXISTE") -> VANISH ROSADO | C28: =IFERROR(VLOOKUP(INVENTARIO[[#This Row],[CODIGO]],BASEDEDATOS[],3,FALSE),"NO EXISTE") -> LAVANDERIA | D28: 12 | E28: 5 | F28: =INVENTARIO[[#This Row],[COMPRAS]]-INVENTARIO[[#This Row],[VENTAS]] -> 7 | G28: 303 | H28: 650 | I28: =INVENTARIO[[#This Row],[PRECIO DE VENTA]]-INVENTARIO[[#This Row],[COSTO UNITARIO]] -> 347 | J28: =INVENTARIO[[#This Row],[COSTO UNITARIO]]*INVENTARIO[[#This Row],[STOCK]] -> 2121 | K28: =+INVENTARIO[[#This Row],[VENTAS]]*INVENTARIO[[#This Row],[UTILIDAD POR PRODUCTO]] -> 1735
A29: A023 | B29: =IFERROR(VLOOKUP(INVENTARIO[[#This Row],[CODIGO]],BASEDEDATOS[],2,FALSE),"NO EXISTE") -> CLORO CONCENTRADO DE 5 LITROS | C29: =IFERROR(VLOOKUP(INVENTARIO[[#This Row],[CODIGO]],BASEDEDATOS[],3,FALSE),"NO EXISTE") -> DESINFECCIÓN | D29: 0 | E29: {=SUM(SUMIF(VENTAS[CODIGO],INVENTARIO!A28:A31,VENTAS[CANTIDAD]))} -> 0 | F29: =INVENTARIO[[#This Row],[COMPRAS]]-INVENTARIO[[#This Row],[VENTAS]] -> 0 | G29: 0 | H29: 0 | I29: =INVENTARIO[[#This Row],[PRECIO DE VENTA]]-INVENTARIO[[#This Row],[COSTO UNITARIO]] -> 0 | J29: =INVENTARIO[[#This Row],[COSTO UNITARIO]]*INVENTARIO[[#This Row],[STOCK]] -> 0 | K29: =+INVENTARIO[[#This Row],[VENTAS]]*INVENTARIO[[#This Row],[UTILIDAD POR PRODUCTO]] -> 0
A30: A024 | B30: =IFERROR(VLOOKUP(INVENTARIO[[#This Row],[CODIGO]],BASEDEDATOS[],2,FALSE),"NO EXISTE") -> CLORINDA DE 1 LITRO | C30: =IFERROR(VLOOKUP(INVENTARIO[[#This Row],[CODIGO]],BASEDEDATOS[],3,FALSE),"NO EXISTE") -> DESINFECCIÓN | D30: 0 | E30: {=SUM(SUMIF(VENTAS[CODIGO],INVENTARIO!A29:A32,VENTAS[CANTIDAD]))} -> 0 | F30: =INVENTARIO[[#This Row],[COMPRAS]]-INVENTARIO[[#This Row],[VENTAS]] -> 0 | G30: 0 | H30: 0 | I30: =INVENTARIO[[#This Row],[PRECIO DE VENTA]]-INVENTARIO[[#This Row],[COSTO UNITARIO]] -> 0 | J30: =INVENTARIO[[#This Row],[COSTO UNITARIO]]*INVENTARIO[[#This Row],[STOCK]] -> 0 | K30: =+INVENTARIO[[#This Row],[VENTAS]]*INVENTARIO[[#This Row],[UTILIDAD POR PRODUCTO]] -> 0
A31: A025 | B31: =IFERROR(VLOOKUP(INVENTARIO[[#This Row],[CODIGO]],BASEDEDATOS[],2,FALSE),"NO EXISTE") -> CLORO GEL CLOROX | C31: =IFERROR(VLOOKUP(INVENTARIO[[#This Row],[CODIGO]],BASEDEDATOS[],3,FALSE),"NO EXISTE") -> DESINFECCIÓN | D31: 0 | E31: 0 | F31: =INVENTARIO[[#This Row],[COMPRAS]]-INVENTARIO[[#This Row],[VENTAS]] -> 0 | G31: 0 | H31: 0 | I31: =INVENTARIO[[#This Row],[PRECIO DE VENTA]]-INVENTARIO[[#This Row],[COSTO UNITARIO]] -> 0 | J31: =INVENTARIO[[#This Row],[COSTO UNITARIO]]*INVENTARIO[[#This Row],[STOCK]] -> 0 | K31: =+INVENTARIO[[#This Row],[VENTAS]]*INVENTARIO[[#This Row],[UTILIDAD POR PRODUCTO]] -> 0
A32: A026 | B32: =IFERROR(VLOOKUP(INVENTARIO[[#This Row],[CODIGO]],BASEDEDATOS[],2,FALSE),"NO EXISTE") -> CLORO IGENIX LIQUIDO | C32: =IFERROR(VLOOKUP(INVENTARIO[[#This Row],[CODIGO]],BASEDEDATOS[],3,FALSE),"NO EXISTE") -> DESINFECCIÓN | D32: 12 | E32: 2 | F32: =INVENTARIO[[#This Row],[COMPRAS]]-INVENTARIO[[#This Row],[VENTAS]] -> 10 | G32: 690 | H32: 1000 | I32: =INVENTARIO[[#This Row],[PRECIO DE VENTA]]-INVENTARIO[[#This Row],[COSTO UNITARIO]] -> 310 | J32: =INVENTARIO[[#This Row],[COSTO UNITARIO]]*INVENTARIO[[#This Row],[STOCK]] -> 6900 | K32: =+INVENTARIO[[#This Row],[VENTAS]]*INVENTARIO[[#This Row],[UTILIDAD POR PRODUCTO]] -> 620
A33: A027 | B33: =IFERROR(VLOOKUP(INVENTARIO[[#This Row],[CODIGO]],BASEDEDATOS[],2,FALSE),"NO EXISTE") -> CLORINDA CLORO GEL | C33: =IFERROR(VLOOKUP(INVENTARIO[[#This Row],[CODIGO]],BASEDEDATOS[],3,FALSE),"NO EXISTE") -> DESINFECCIÓN | D33: 24 | E33: 5 | F33: =INVENTARIO[[#This Row],[COMPRAS]]-INVENTARIO[[#This Row],[VENTAS]] -> 19 | G33: 1050 | H33: 1900 | I33: =INVENTARIO[[#This Row],[PRECIO DE VENTA]]-INVENTARIO[[#This Row],[COSTO UNITARIO]] -> 850 | J33: =INVENTARIO[[#This Row],[COSTO UNITARIO]]*INVENTARIO[[#This Row],[STOCK]] -> 19950 | K33: =+INVENTARIO[[#This Row],[VENTAS]]*INVENTARIO[[#This Row],[UTILIDAD POR PRODUCTO]] -> 4250
A34: A028 | B34: =IFERROR(VLOOKUP(INVENTARIO[[#This Row],[CODIGO]],BASEDEDATOS[],2,FALSE),"NO EXISTE") -> CLORINDA CLORO GEL EXCEL MORADO | C34: =IFERROR(VLOOKUP(INVENTARIO[[#This Row],[CODIGO]],BASEDEDATOS[],3,FALSE),"NO EXISTE") -> DESINFECCIÓN | D34: 12 | E34: 0 | F34: =INVENTARIO[[#This Row],[COMPRAS]]-INVENTARIO[[#This Row],[VENTAS]] -> 12 | G34: 797 | H34: 1300 | I34: =INVENTARIO[[#This Row],[PRECIO DE VENTA]]-INVENTARIO[[#This Row],[COSTO UNITARIO]] -> 503 | J34: =INVENTARIO[[#This Row],[COSTO UNITARIO]]*INVENTARIO[[#This Row],[STOCK]] -> 9564 | K34: =+INVENTARIO[[#This Row],[VENTAS]]*INVENTARIO[[#This Row],[UTILIDAD POR PRODUCTO]] -> 0
A35: A029 | B35: =IFERROR(VLOOKUP(INVENTARIO[[#This Row],[CODIGO]],BASEDEDATOS[],2,FALSE),"NO EXISTE") -> CLORINDA CLORO GEL EXCEL AMARILLO | C35: =IFERROR(VLOOKUP(INVENTARIO[[#This Row],[CODIGO]],BASEDEDATOS[],3,FALSE),"NO EXISTE") -> DESINFECCIÓN | D35: 12 | E35: 2 | F35: =INVENTARIO[[#This Row],[COMPRAS]]-INVENTARIO[[#This Row],[VENTAS]] -> 10 | G35: 797 | H35: 1300 | I35: =INVENTARIO[[#This Row],[PRECIO DE VENTA]]-INVENTARIO[[#This Row],[COSTO UNITARIO]] -> 503 | J35: =INVENTARIO[[#This Row],[COSTO UNITARIO]]*INVENTARIO[[#This Row],[STOCK]] -> 7970 | K35: =+INVENTARIO[[#This Row],[VENTAS]]*INVENTARIO[[#This Row],[UTILIDAD POR PRODUCTO]] -> 1006
A36: A030 | B36: =IFERROR(VLOOKUP(INVENTARIO[[#This Row],[CODIGO]],BASEDEDATOS[],2,FALSE),"NO EXISTE") -> ANTIGRASA SPUM DE 2 LITROS | C36: =IFERROR(VLOOKUP(INVENTARIO[[#This Row],[CODIGO]],BASEDEDATOS[],3,FALSE),"NO EXISTE") -> COCINA | D36: 10 | E36: 2 | F36: =INVENTARIO[[#This Row],[COMPRAS]]-INVENTARIO[[#This Row],[VENTAS]] -> 8 | G36: 1049 | H36: 2000 | I36: =INVENTARIO[[#This Row],[PRECIO DE VENTA]]-INVENTARIO[[#This Row],[COSTO UNITARIO]] -> 951 | J36: =INVENTARIO[[#This Row],[COSTO UNITARIO]]*INVENTARIO[[#This Row],[STOCK]] -> 8392 | K36: =+INVENTARIO[[#This Row],[VENTAS]]*INVENTARIO[[#This Row],[UTILIDAD POR PRODUCTO]] -> 1902
A37: A031 | B37: =IFERROR(VLOOKUP(INVENTARIO[[#This Row],[CODIGO]],BASEDEDATOS[],2,FALSE),"NO EXISTE") -> ANTIGRASA SPUM DE 500 ML | C37: =IFERROR(VLOOKUP(INVENTARIO[[#This Row],[CODIGO]],BASEDEDATOS[],3,FALSE),"NO EXISTE") -> COCINA | D37: 12 | E37: 6 | F37: =INVENTARIO[[#This Row],[COMPRAS]]-INVENTARIO[[#This Row],[VENTAS]] -> 6 | G37: 700 | H37: 1400 | I37: =INVENTARIO[[#This Row],[PRECIO DE VENTA]]-INVENTARIO[[#This Row],[COSTO UNITARIO]] -> 700 | J37: =INVENTARIO[[#This Row],[COSTO UNITARIO]]*INVENTARIO[[#This Row],[STOCK]] -> 4200 | K37: =+INVENTARIO[[#This Row],[VENTAS]]*INVENTARIO[[#This Row],[UTILIDAD POR PRODUCTO]] -> 4200
A38: A032 | B38: =IFERROR(VLOOKUP(INVENTARIO[[#This Row],[CODIGO]],BASEDEDATOS[],2,FALSE),"NO EXISTE") -> SACASARRO SPUM DE 2 LITROS | C38: =IFERROR(VLOOKUP(INVENTARIO[[#This Row],[CODIGO]],BASEDEDATOS[],3,FALSE),"NO EXISTE") -> COCINA | D38: 9 | E38: 2 | F38: =INVENTARIO[[#This Row],[COMPRAS]]-INVENTARIO[[#This Row],[VENTAS]] -> 7 | G38: 888 | H38: 2300 | I38: =INVENTARIO[[#This Row],[PRECIO DE VENTA]]-INVENTARIO[[#This Row],[COSTO UNITARIO]] -> 1412 | J38: =INVENTARIO[[#This Row],[COSTO UNITARIO]]*INVENTARIO[[#This Row],[STOCK]] -> 6216 | K38: =+INVENTARIO[[#This Row],[VENTAS]]*INVENTARIO[[#This Row],[UTILIDAD POR PRODUCTO]] -> 2824
A39: A033 | B39: =IFERROR(VLOOKUP(INVENTARIO[[#This Row],[CODIGO]],BASEDEDATOS[],2,FALSE),"NO EXISTE") -> SACASARRO SPUM DE 500 ML | C39: =IFERROR(VLOOKUP(INVENTARIO[[#This Row],[CODIGO]],BASEDEDATOS[],3,FALSE),"NO EXISTE") -> COCINA | D39: 10 | E39: 0 | F39: =INVENTARIO[[#This Row],[COMPRAS]]-INVENTARIO[[#This Row],[VENTAS]] -> 10 | G39: 970 | H39: 2000 | I39: =INVENTARIO[[#This Row],[PRECIO DE VENTA]]-INVENTARIO[[#This Row],[COSTO UNITARIO]] -> 1030 | J39: =INVENTARIO[[#This Row],[COSTO UNITARIO]]*INVENTARIO[[#This Row],[STOCK]] -> 9700 | K39: =+INVENTARIO[[#This Row],[VENTAS]]*INVENTARIO[[#This Row],[UTILIDAD POR PRODUCTO]] -> 0
A40: A034 | B40: =IFERROR(VLOOKUP(INVENTARIO[[#This Row],[CODIGO]],BASEDEDATOS[],2,FALSE),"NO EXISTE") -> LAVALOSA SPUM DE 1 LITRO | C40: =IFERROR(VLOOKUP(INVENTARIO[[#This Row],[CODIGO]],BASEDEDATOS[],3,FALSE),"NO EXISTE") -> COCINA | D40: 12 | E40: 2 | F40: =INVENTARIO[[#This Row],[COMPRAS]]-INVENTARIO[[#This Row],[VENTAS]] -> 10 | G40: 650 | H40: 1400 | I40: =INVENTARIO[[#This Row],[PRECIO DE VENTA]]-INVENTARIO[[#This Row],[COSTO UNITARIO]] -> 750 | J40: =INVENTARIO[[#This Row],[COSTO UNITARIO]]*INVENTARIO[[#This Row],[STOCK]] -> 6500 | K40: =+INVENTARIO[[#This Row],[VENTAS]]*INVENTARIO[[#This Row],[UTILIDAD POR PRODUCTO]] -> 1500
A41: A035 | B41: =IFERROR(VLOOKUP(INVENTARIO[[#This Row],[CODIGO]],BASEDEDATOS[],2,FALSE),"NO EXISTE") -> LAVALOSA SPUM DE 2 LITROS | C41: =IFERROR(VLOOKUP(INVENTARIO[[#This Row],[CODIGO]],BASEDEDATOS[],3,FALSE),"NO EXISTE") -> COCINA | D41: 9 | E41: 3 | F41: =INVENTARIO[[#This Row],[COMPRAS]]-INVENTARIO[[#This Row],[VENTAS]] -> 6 | G41: 1010 | H41: 2300 | I41: =INVENTARIO[[#This Row],[PRECIO DE VENTA]]-INVENTARIO[[#This Row],[COSTO UNITARIO]] -> 1290 | J41: =INVENTARIO[[#This Row],[COSTO UNITARIO]]*INVENTARIO[[#This Row],[STOCK]] -> 6060 | K41: =+INVENTARIO[[#This Row],[VENTAS]]*INVENTARIO[[#This Row],[UTILIDAD POR PRODUCTO]] -> 3870
A42: A036 | B42: =IFERROR(VLOOKUP(INVENTARIO[[#This Row],[CODIGO]],BASEDEDATOS[],2,FALSE),"NO EXISTE") -> LAVALOSA SPUM DE 5 LITROS | C42: =IFERROR(VLOOKUP(INVENTARIO[[#This Row],[CODIGO]],BASEDEDATOS[],3,FALSE),"NO EXISTE") -> COCINA | D42: 10 | E42: 0 | F42: =INVENTARIO[[#This Row],[COMPRAS]]-INVENTARIO[[#This Row],[VENTAS]] -> 10 | G42: 2300 | H42: 4000 | I42: =INVENTARIO[[#This Row],[PRECIO DE VENTA]]-INVENTARIO[[#This Row],[COSTO UNITARIO]] -> 1700 | J42: =INVENTARIO[[#This Row],[COSTO UNITARIO]]*INVENTARIO[[#This Row],[STOCK]] -> 23000 | K42: =+INVENTARIO[[#This Row],[VENTAS]]*INVENTARIO[[#This Row],[UTILIDAD POR PRODUCTO]] -> 0
A43: A037 | B43: =IFERROR(VLOOKUP(INVENTARIO[[#This Row],[CODIGO]],BASEDEDATOS[],2,FALSE),"NO EXISTE") -> LAVALOSA QUIX | C43: =IFERROR(VLOOKUP(INVENTARIO[[#This Row],[CODIGO]],BASEDEDATOS[],3,FALSE),"NO EXISTE") -> COCINA | D43: 0 | E43: {=SUM(SUMIF(VENTAS[CODIGO],INVENTARIO!A42:A45,VENTAS[CANTIDAD]))} -> 0 | F43: =INVENTARIO[[#This Row],[COMPRAS]]-INVENTARIO[[#This Row],[VENTAS]] -> 0 | G43: 0 | H43: 0 | I43: =INVENTARIO[[#This Row],[PRECIO DE VENTA]]-INVENTARIO[[#This Row],[COSTO UNITARIO]] -> 0 | J43: =INVENTARIO[[#This Row],[COSTO UNITARIO]]*INVENTARIO[[#This Row],[STOCK]] -> 0 | K43: =+INVENTARIO[[#This Row],[VENTAS]]*INVENTARIO[[#This Row],[UTILIDAD POR PRODUCTO]] -> 0
A44: A038 | B44: =IFERROR(VLOOKUP(INVENTARIO[[#This Row],[CODIGO]],BASEDEDATOS[],2,FALSE),"NO EXISTE") -> CIF | C44: =IFERROR(VLOOKUP(INVENTARIO[[#This Row],[CODIGO]],BASEDEDATOS[],3,FALSE),"NO EXISTE") -> COCINA | D44: 12 | E44: 6 | F44: =INVENTARIO[[#This Row],[COMPRAS]]-INVENTARIO[[#This Row],[VENTAS]] -> 6 | G44: 1010 | H44: 2200 | I44: =INVENTARIO[[#This Row],[PRECIO DE VENTA]]-INVENTARIO[[#This Row],[COSTO UNITARIO]] -> 1190 | J44: =INVENTARIO[[#This Row],[COSTO UNITARIO]]*INVENTARIO[[#This Row],[STOCK]] -> 6060 | K44: =+INVENTARIO[[#This Row],[VENTAS]]*INVENTARIO[[#This Row],[UTILIDAD POR PRODUCTO]] -> 7140
A45: A039 | B45: =IFERROR(VLOOKUP(INVENTARIO[[#This Row],[CODIGO]],BASEDEDATOS[],2,FALSE),"NO EXISTE") -> LUSTRA MUEBLES | C45: =IFERROR(VLOOKUP(INVENTARIO[[#This Row],[CODIGO]],BASEDEDATOS[],3,FALSE),"NO EXISTE") -> COCINA | D45: 6 | E45: 1 | F45: =INVENTARIO[[#This Row],[COMPRAS]]-INVENTARIO[[#This Row],[VENTAS]] -> 5 | G45: 1090 | H45: 1500 | I45: =INVENTARIO[[#This Row],[PRECIO DE VENTA]]-INVENTARIO[[#This Row],[COSTO UNITARIO]] -> 410 | J45: =INVENTARIO[[#This Row],[COSTO UNITARIO]]*INVENTARIO[[#This Row],[STOCK]] -> 5450 | K45: =+INVENTARIO[[#This Row],[VENTAS]]*INVENTARIO[[#This Row],[UTILIDAD POR PRODUCTO]] -> 410
A46: A040 | B46: =IFERROR(VLOOKUP(INVENTARIO[[#This Row],[CODIGO]],BASEDEDATOS[],2,FALSE),"NO EXISTE") -> LIMPIA VIDRIOS DE 500CC | C46: =IFERROR(VLOOKUP(INVENTARIO[[#This Row],[CODIGO]],BASEDEDATOS[],3,FALSE),"NO EXISTE") -> COCINA | D46: 12 | E46: 8 | F46: =INVENTARIO[[#This Row],[COMPRAS]]-INVENTARIO[[#This Row],[VENTAS]] -> 4 | G46: 900 | H46: 2000 | I46: =INVENTARIO[[#This Row],[PRECIO DE VENTA]]-INVENTARIO[[#This Row],[COSTO UNITARIO]] -> 1100 | J46: =INVENTARIO[[#This Row],[COSTO UNITARIO]]*INVENTARIO[[#This Row],[STOCK]] -> 3600 | K46: =+INVENTARIO[[#This Row],[VENTAS]]*INVENTARIO[[#This Row],[UTILIDAD POR PRODUCTO]] -> 8800
A47: A041 | B47: =IFERROR(VLOOKUP(INVENTARIO[[#This Row],[CODIGO]],BASEDEDATOS[],2,FALSE),"NO EXISTE") -> LIMPIA PISOS FLOTANTE | C47: =IFERROR(VLOOKUP(INVENTARIO[[#This Row],[CODIGO]],BASEDEDATOS[],3,FALSE),"NO EXISTE") -> COCINA | D47: 12 | E47: 2 | F47: =INVENTARIO[[#This Row],[COMPRAS]]-INVENTARIO[[#This Row],[VENTAS]] -> 10 | G47: 625 | H47: 1000 | I47: =INVENTARIO[[#This Row],[PRECIO DE VENTA]]-INVENTARIO[[#This Row],[COSTO UNITARIO]] -> 375 | J47: =INVENTARIO[[#This Row],[COSTO UNITARIO]]*INVENTARIO[[#This Row],[STOCK]] -> 6250 | K47: =+INVENTARIO[[#This Row],[VENTAS]]*INVENTARIO[[#This Row],[UTILIDAD POR PRODUCTO]] -> 750
A48: A042 | B48: =IFERROR(VLOOKUP(INVENTARIO[[#This Row],[CODIGO]],BASEDEDATOS[],2,FALSE),"NO EXISTE") -> VIRUTILLA | C48: =IFERROR(VLOOKUP(INVENTARIO[[#This Row],[CODIGO]],BASEDEDATOS[],3,FALSE),"NO EXISTE") -> COCINA | D48: 24 | E48: 8 | F48: =INVENTARIO[[#This Row],[COMPRAS]]-INVENTARIO[[#This Row],[VENTAS]] -> 16 | G48: 500 | H48: 1000 | I48: =INVENTARIO[[#This Row],[PRECIO DE VENTA]]-INVENTARIO[[#This Row],[COSTO UNITARIO]] -> 500 | J48: =INVENTARIO[[#This Row],[COSTO UNITARIO]]*INVENTARIO[[#This Row],[STOCK]] -> 8000 | K48: =+INVENTARIO[[#This Row],[VENTAS]]*INVENTARIO[[#This Row],[UTILIDAD POR PRODUCTO]] -> 4000
A49: A043 | B49: =IFERROR(VLOOKUP(INVENTARIO[[#This Row],[CODIGO]],BASEDEDATOS[],2,FALSE),"NO EXISTE") -> LIMPIA PISOS SPUM COLOR ROJO | C49: =IFERROR(VLOOKUP(INVENTARIO[[#This Row],[CODIGO]],BASEDEDATOS[],3,FALSE),"NO EXISTE") -> SUPERFICIE | D49: 9 | E49: 0 | F49: =INVENTARIO[[#This Row],[COMPRAS]]-INVENTARIO[[#This Row],[VENTAS]] -> 9 | H49: 2000 | I49: =INVENTARIO[[#This Row],[PRECIO DE VENTA]]-INVENTARIO[[#This Row],[COSTO UNITARIO]] -> 2000 | J49: =INVENTARIO[[#This Row],[COSTO UNITARIO]]*INVENTARIO[[#This Row],[STOCK]] -> 0 | K49: =+INVENTARIO[[#This Row],[VENTAS]]*INVENTARIO[[#This Row],[UTILIDAD POR PRODUCTO]] -> 0
A50: A044 | B50: =IFERROR(VLOOKUP(INVENTARIO[[#This Row],[CODIGO]],BASEDEDATOS[],2,FALSE),"NO EXISTE") -> LIMPIA PISOS SPUM COLOR AZUL | C50: =IFERROR(VLOOKUP(INVENTARIO[[#This Row],[CODIGO]],BASEDEDATOS[],3,FALSE),"NO EXISTE") -> SUPERFICIE | D50: 9 | E50: 0 | F50: =INVENTARIO[[#This Row],[COMPRAS]]-INVENTARIO[[#This Row],[VENTAS]] -> 9 | H50: 2000 | I50: =INVENTARIO[[#This Row],[PRECIO DE VENTA]]-INVENTARIO[[#This Row],[COSTO UNITARIO]] -> 2000 | J50: =INVENTARIO[[#This Row],[COSTO UNITARIO]]*INVENTARIO[[#This Row],[STOCK]] -> 0 | K50: =+INVENTARIO[[#This Row],[VENTAS]]*INVENTARIO[[#This Row],[UTILIDAD POR PRODUCTO]] -> 0
A51: A045 | B51: =IFERROR(VLOOKUP(INVENTARIO[[#This Row],[CODIGO]],BASEDEDATOS[],2,FALSE),"NO EXISTE") -> LIMPIA PISOS BRILLEX AMARILLO | C51: =IFERROR(VLOOKUP(INVENTARIO[[#This Row],[CODIGO]],BASEDEDATOS[],3,FALSE),"NO EXISTE") -> SUPERFICIE | D51: 12 | E51: 2 | F51: =INVENTARIO[[#This Row],[COMPRAS]]-INVENTARIO[[#This Row],[VENTAS]] -> 10 | G51: 698 | H51: 1000 | I51: =INVENTARIO[[#This Row],[PRECIO DE VENTA]]-INVENTARIO[[#This Row],[COSTO UNITARIO]] -> 302 | J51: =INVENTARIO[[#This Row],[COSTO UNITARIO]]*INVENTARIO[[#This Row],[STOCK]] -> 6980 | K51: =+INVENTARIO[[#This Row],[VENTAS]]*INVENTARIO[[#This Row],[UTILIDAD POR PRODUCTO]] -> 604
A52: A046 | B52: =IFERROR(VLOOKUP(INVENTARIO[[#This Row],[CODIGO]],BASEDEDATOS[],2,FALSE),"NO EXISTE") -> LIMPIA PISOS AROMAX AZUL | C52: =IFERROR(VLOOKUP(INVENTARIO[[#This Row],[CODIGO]],BASEDEDATOS[],3,FALSE),"NO EXISTE") -> SUPERFICIE | D52: 12 | E52: 12 | F52: =INVENTARIO[[#This Row],[COMPRAS]]-INVENTARIO[[#This Row],[VENTAS]] -> 0 | G52: 382 | H52: 1000 | I52: =INVENTARIO[[#This Row],[PRECIO DE VENTA]]-INVENTARIO[[#This Row],[COSTO UNITARIO]] -> 618 | J52: =INVENTARIO[[#This Row],[COSTO UNITARIO]]*INVENTARIO[[#This Row],[STOCK]] -> 0 | K52: =+INVENTARIO[[#This Row],[VENTAS]]*INVENTARIO[[#This Row],[UTILIDAD POR PRODUCTO]] -> 7416
A53: A047 | B53: =IFERROR(VLOOKUP(INVENTARIO[[#This Row],[CODIGO]],BASEDEDATOS[],2,FALSE),"NO EXISTE") -> LIMPIA PISOS AROMAX ROSADO | C53: =IFERROR(VLOOKUP(INVENTARIO[[#This Row],[CODIGO]],BASEDEDATOS[],3,FALSE),"NO EXISTE") -> SUPERFICIE | D53: 12 | E53: 12 | F53: =INVENTARIO[[#This Row],[COMPRAS]]-INVENTARIO[[#This Row],[VENTAS]] -> 0 | G53: 382 | H53: 1000 | I53: =INVENTARIO[[#This Row],[PRECIO DE VENTA]]-INVENTARIO[[#This Row],[COSTO UNITARIO]] -> 618 | J53: =INVENTARIO[[#This Row],[COSTO UNITARIO]]*INVENTARIO[[#This Row],[STOCK]] -> 0 | K53: =+INVENTARIO[[#This Row],[VENTAS]]*INVENTARIO[[#This Row],[UTILIDAD POR PRODUCTO]] -> 7416
A54: A048 | B54: =IFERROR(VLOOKUP(INVENTARIO[[#This Row],[CODIGO]],BASEDEDATOS[],2,FALSE),"NO EXISTE") -> LIMPIA PISOS AROMAX MORADO | C54: =IFERROR(VLOOKUP(INVENTARIO[[#This Row],[CODIGO]],BASEDEDATOS[],3,FALSE),"NO EXISTE") -> SUPERFICIE | D54: 132 | E54: 8 | F54: =INVENTARIO[[#This Row],[COMPRAS]]-INVENTARIO[[#This Row],[VENTAS]] -> 124 | G54: 382 | H54: 1000 | I54: =INVENTARIO[[#This Row],[PRECIO DE VENTA]]-INVENTARIO[[#This Row],[COSTO UNITARIO]] -> 618 | J54: =INVENTARIO[[#This Row],[COSTO UNITARIO]]*INVENTARIO[[#This Row],[STOCK]] -> 47368 | K54: =+INVENTARIO[[#This Row],[VENTAS]]*INVENTARIO[[#This Row],[UTILIDAD POR PRODUCTO]] -> 4944
A55: A049 | B55: =IFERROR(VLOOKUP(INVENTARIO[[#This Row],[CODIGO]],BASEDEDATOS[],2,FALSE),"NO EXISTE") -> LIMPIA PISOS POETT ROSADO | C55: =IFERROR(VLOOKUP(INVENTARIO[[#This Row],[CODIGO]],BASEDEDATOS[],3,FALSE),"NO EXISTE") -> SUPERFICIE | D55: 12 | E55: 11 | F55: =INVENTARIO[[#This Row],[COMPRAS]]-INVENTARIO[[#This Row],[VENTAS]] -> 1 | G55: 1010 | H55: 1600 | I55: =INVENTARIO[[#This Row],[PRECIO DE VENTA]]-INVENTARIO[[#This Row],[COSTO UNITARIO]] -> 590 | J55: =INVENTARIO[[#This Row],[COSTO UNITARIO]]*INVENTARIO[[#This Row],[STOCK]] -> 1010 | K55: =+INVENTARIO[[#This Row],[VENTAS]]*INVENTARIO[[#This Row],[UTILIDAD POR PRODUCTO]] -> 6490
A56: A050 | B56: =IFERROR(VLOOKUP(INVENTARIO[[#This Row],[CODIGO]],BASEDEDATOS[],2,FALSE),"NO EXISTE") -> LIMPIA PISOS POETT MORADO OSCURO | C56: =IFERROR(VLOOKUP(INVENTARIO[[#This Row],[CODIGO]],BASEDEDATOS[],3,FALSE),"NO EXISTE") -> SUPERFICIE | D56: 6 | E56: 4 | F56: =INVENTARIO[[#This Row],[COMPRAS]]-INVENTARIO[[#This Row],[VENTAS]] -> 2 | G56: 1010 | H56: 1600 | I56: =INVENTARIO[[#This Row],[PRECIO DE VENTA]]-INVENTARIO[[#This Row],[COSTO UNITARIO]] -> 590 | J56: =INVENTARIO[[#This Row],[COSTO UNITARIO]]*INVENTARIO[[#This Row],[STOCK]] -> 2020 | K56: =+INVENTARIO[[#This Row],[VENTAS]]*INVENTARIO[[#This Row],[UTILIDAD POR PRODUCTO]] -> 2360
A57: A051 | B57: =IFERROR(VLOOKUP(INVENTARIO[[#This Row],[CODIGO]],BASEDEDATOS[],2,FALSE),"NO EXISTE") -> ESCOBILLON | C57: =IFERROR(VLOOKUP(INVENTARIO[[#This Row],[CODIGO]],BASEDEDATOS[],3,FALSE),"NO EXISTE") -> SUPERFICIE | D57: 36 | E57: 2 | F57: =INVENTARIO[[#This Row],[COMPRAS]]-INVENTARIO[[#This Row],[VENTAS]] -> 34 | G57: 781 | H57: 1200 | I57: =INVENTARIO[[#This Row],[PRECIO DE VENTA]]-INVENTARIO[[#This Row],[COSTO UNITARIO]] -> 419 | J57: =INVENTARIO[[#This Row],[COSTO UNITARIO]]*INVENTARIO[[#This Row],[STOCK]] -> 26554 | K57: =+INVENTARIO[[#This Row],[VENTAS]]*INVENTARIO[[#This Row],[UTILIDAD POR PRODUCTO]] -> 838
A58: A052 | B58: =IFERROR(VLOOKUP(INVENTARIO[[#This Row],[CODIGO]],BASEDEDATOS[],2,FALSE),"NO EXISTE") -> LIMPIA PISOS POETT MORADO CLARO | C58: =IFERROR(VLOOKUP(INVENTARIO[[#This Row],[CODIGO]],BASEDEDATOS[],3,FALSE),"NO EXISTE") -> SUPERFICIE | D58: 3 | E58: {=SUM(SUMIF(VENTAS[CODIGO],INVENTARIO!A57:A60,VENTAS[CANTIDAD]))} -> 0 | F58: =INVENTARIO[[#This Row],[COMPRAS]]-INVENTARIO[[#This Row],[VENTAS]] -> 3 | G58: 1010 | H58: 1600 | I58: =INVENTARIO[[#This Row],[PRECIO DE VENTA]]-INVENTARIO[[#This Row],[COSTO UNITARIO]] -> 590 | J58: =INVENTARIO[[#This Row],[COSTO UNITARIO]]*INVENTARIO[[#This Row],[STOCK]] -> 3030 | K58: =+INVENTARIO[[#This Row],[VENTAS]]*INVENTARIO[[#This Row],[UTILIDAD POR PRODUCTO]] -> 0
A59: A053 | B59: =IFERROR(VLOOKUP(INVENTARIO[[#This Row],[CODIGO]],BASEDEDATOS[],2,FALSE),"NO EXISTE") -> LIMPIA PISOS POETT AZUL | C59: =IFERROR(VLOOKUP(INVENTARIO[[#This Row],[CODIGO]],BASEDEDATOS[],3,FALSE),"NO EXISTE") -> SUPERFICIE | D59: 3 | E59: {=SUM(SUMIF(VENTAS[CODIGO],INVENTARIO!A58:A61,VENTAS[CANTIDAD]))} -> 0 | F59: =INVENTARIO[[#This Row],[COMPRAS]]-INVENTARIO[[#This Row],[VENTAS]] -> 3 | G59: 1010 | H59: 1600 | I59: =INVENTARIO[[#This Row],[PRECIO DE VENTA]]-INVENTARIO[[#This Row],[COSTO UNITARIO]] -> 590 | J59: =INVENTARIO[[#This Row],[COSTO UNITARIO]]*INVENTARIO[[#This Row],[STOCK]] -> 3030 | K59: =+INVENTARIO[[#This Row],[VENTAS]]*INVENTARIO[[#This Row],[UTILIDAD POR PRODUCTO]] -> 0
A60: A054 | B60: =IFERROR(VLOOKUP(INVENTARIO[[#This Row],[CODIGO]],BASEDEDATOS[],2,FALSE),"NO EXISTE") -> CERA DE 1 LITRO | C60: =IFERROR(VLOOKUP(INVENTARIO[[#This Row],[CODIGO]],BASEDEDATOS[],3,FALSE),"NO EXISTE") -> SUPERFICIE | D60: 12 | E60: {=SUM(SUMIF(VENTAS[CODIGO],INVENTARIO!A59:A62,VENTAS[CANTIDAD]))} -> 0 | F60: =INVENTARIO[[#This Row],[COMPRAS]]-INVENTARIO[[#This Row],[VENTAS]] -> 12 | G60: 749 | H60: 1400 | I60: =INVENTARIO[[#This Row],[PRECIO DE VENTA]]-INVENTARIO[[#This Row],[COSTO UNITARIO]] -> 651 | J60: =INVENTARIO[[#This Row],[COSTO UNITARIO]]*INVENTARIO[[#This Row],[STOCK]] -> 8988 | K60: =+INVENTARIO[[#This Row],[VENTAS]]*INVENTARIO[[#This Row],[UTILIDAD POR PRODUCTO]] -> 0
A61: A055 | B61: =IFERROR(VLOOKUP(INVENTARIO[[#This Row],[CODIGO]],BASEDEDATOS[],2,FALSE),"NO EXISTE") -> CERA DE 2 LITROS | C61: =IFERROR(VLOOKUP(INVENTARIO[[#This Row],[CODIGO]],BASEDEDATOS[],3,FALSE),"NO EXISTE") -> SUPERFICIE | D61: 9 | E61: {=SUM(SUMIF(VENTAS[CODIGO],INVENTARIO!A60:A63,VENTAS[CANTIDAD]))} -> 0 | F61: =INVENTARIO[[#This Row],[COMPRAS]]-INVENTARIO[[#This Row],[VENTAS]] -> 9 | G61: 1299 | H61: 2300 | I61: =INVENTARIO[[#This Row],[PRECIO DE VENTA]]-INVENTARIO[[#This Row],[COSTO UNITARIO]] -> 1001 | J61: =INVENTARIO[[#This Row],[COSTO UNITARIO]]*INVENTARIO[[#This Row],[STOCK]] -> 11691 | K61: =+INVENTARIO[[#This Row],[VENTAS]]*INVENTARIO[[#This Row],[UTILIDAD POR PRODUCTO]] -> 0
A62: A056 | B62: =IFERROR(VLOOKUP(INVENTARIO[[#This Row],[CODIGO]],BASEDEDATOS[],2,FALSE),"NO EXISTE") -> PASTILLAS DE CLORO CHICAS PARA BAÑO | C62: =IFERROR(VLOOKUP(INVENTARIO[[#This Row],[CODIGO]],BASEDEDATOS[],3,FALSE),"NO EXISTE") -> SUPERFICIE | D62: 50 | E62: 15 | F62: =INVENTARIO[[#This Row],[COMPRAS]]-INVENTARIO[[#This Row],[VENTAS]] -> 35 | G62: 70 | H62: 1000 | I62: =INVENTARIO[[#This Row],[PRECIO DE VENTA]]-INVENTARIO[[#This Row],[COSTO UNITARIO]] -> 930 | J62: =INVENTARIO[[#This Row],[COSTO UNITARIO]]*INVENTARIO[[#This Row],[STOCK]] -> 2450 | K62: =+INVENTARIO[[#This Row],[VENTAS]]*INVENTARIO[[#This Row],[UTILIDAD POR PRODUCTO]] -> 13950
A63: A057 | B63: =IFERROR(VLOOKUP(INVENTARIO[[#This Row],[CODIGO]],BASEDEDATOS[],2,FALSE),"NO EXISTE") -> TOALLITAS DESINFECTANTE IGENIX | C63: =IFERROR(VLOOKUP(INVENTARIO[[#This Row],[CODIGO]],BASEDEDATOS[],3,FALSE),"NO EXISTE") -> SUPERFICIE | D63: 12 | E63: 3 | F63: =INVENTARIO[[#This Row],[COMPRAS]]-INVENTARIO[[#This Row],[VENTAS]] -> 9 | G63: 0 | H63: 2500 | I63: =INVENTARIO[[#This Row],[PRECIO DE VENTA]]-INVENTARIO[[#This Row],[COSTO UNITARIO]] -> 2500 | J63: =INVENTARIO[[#This Row],[COSTO UNITARIO]]*INVENTARIO[[#This Row],[STOCK]] -> 0 | K63: =+INVENTARIO[[#This Row],[VENTAS]]*INVENTARIO[[#This Row],[UTILIDAD POR PRODUCTO]] -> 7500
A64: A058 | B64: =IFERROR(VLOOKUP(INVENTARIO[[#This Row],[CODIGO]],BASEDEDATOS[],2,FALSE),"NO EXISTE") -> DESODRANTE AMBIENTAL AHORRITO | C64: =IFERROR(VLOOKUP(INVENTARIO[[#This Row],[CODIGO]],BASEDEDATOS[],3,FALSE),"NO EXISTE") -> AMBIENTADORES | D64: 0 | E64: {=SUM(SUMIF(VENTAS[CODIGO],INVENTARIO!A63:A66,VENTAS[CANTIDAD]))} -> 0 | F64: =INVENTARIO[[#This Row],[COMPRAS]]-INVENTARIO[[#This Row],[VENTAS]] -> 0 | I64: =INVENTARIO[[#This Row],[PRECIO DE VENTA]]-INVENTARIO[[#This Row],[COSTO UNITARIO]] -> 0 | J64: =INVENTARIO[[#This Row],[COSTO UNITARIO]]*INVENTARIO[[#This Row],[STOCK]] -> 0 | K64: =+INVENTARIO[[#This Row],[VENTAS]]*INVENTARIO[[#This Row],[UTILIDAD POR PRODUCTO]] -> 0
A65: A059 | B65: =IFERROR(VLOOKUP(INVENTARIO[[#This Row],[CODIGO]],BASEDEDATOS[],2,FALSE),"NO EXISTE") -> DESODRANTE AMBIENTAL AROM LAVANDA | C65: =IFERROR(VLOOKUP(INVENTARIO[[#This Row],[CODIGO]],BASEDEDATOS[],3,FALSE),"NO EXISTE") -> AMBIENTADORES | D65: {=SUMPRODUCT(SUMIF(COMPRAS[CODIGO],INVENTARIO!A64:A66,COMPRAS[CANTIDAD]))} -> 0 | E65: {=SUM(SUMIF(VENTAS[CODIGO],INVENTARIO!A64:A67,VENTAS[CANTIDAD]))} -> 0 | F65: =INVENTARIO[[#This Row],[COMPRAS]]-INVENTARIO[[#This Row],[VENTAS]] -> 0 | I65: =INVENTARIO[[#This Row],[PRECIO DE VENTA]]-INVENTARIO[[#This Row],[COSTO UNITARIO]] -> 0 | J65: =INVENTARIO[[#This Row],[COSTO UNITARIO]]*INVENTARIO[[#This Row],[STOCK]] -> 0 | K65: =+INVENTARIO[[#This Row],[VENTAS]]*INVENTARIO[[#This Row],[UTILIDAD POR PRODUCTO]] -> 0
A66: A060 | B66: =IFERROR(VLOOKUP(INVENTARIO[[#This Row],[CODIGO]],BASEDEDATOS[],2,FALSE),"NO EXISTE") -> DESODRANTE AMBIENTAL AROM LIMON | C66: =IFERROR(VLOOKUP(INVENTARIO[[#This Row],[CODIGO]],BASEDEDATOS[],3,FALSE),"NO EXISTE") -> AMBIENTADORES | D66: 12 | E66: 0 | F66: =INVENTARIO[[#This Row],[COMPRAS]]-INVENTARIO[[#This Row],[VENTAS]] -> 12 | G66: 890 | H66: 1300 | I66: =INVENTARIO[[#This Row],[PRECIO DE VENTA]]-INVENTARIO[[#This Row],[COSTO UNITARIO]] -> 410 | J66: =INVENTARIO[[#This Row],[COSTO UNITARIO]]*INVENTARIO[[#This Row],[STOCK]] -> 10680 | K66: =+INVENTARIO[[#This Row],[VENTAS]]*INVENTARIO[[#This Row],[UTILIDAD POR PRODUCTO]] -> 0
A67: A061 | B67: =IFERROR(VLOOKUP(INVENTARIO[[#This Row],[CODIGO]],BASEDEDATOS[],2,FALSE),"NO EXISTE") -> DESODRANTE AMBIENTAL POETT ROSADO OSCURO | C67: =IFERROR(VLOOKUP(INVENTARIO[[#This Row],[CODIGO]],BASEDEDATOS[],3,FALSE),"NO EXISTE") -> AMBIENTADORES | D67: 4 | E67: 3 | F67: =INVENTARIO[[#This Row],[COMPRAS]]-INVENTARIO[[#This Row],[VENTAS]] -> 1 | H67: 2000 | I67: =INVENTARIO[[#This Row],[PRECIO DE VENTA]]-INVENTARIO[[#This Row],[COSTO UNITARIO]] -> 2000 | J67: =INVENTARIO[[#This Row],[COSTO UNITARIO]]*INVENTARIO[[#This Row],[STOCK]] -> 0 | K67: =+INVENTARIO[[#This Row],[VENTAS]]*INVENTARIO[[#This Row],[UTILIDAD POR PRODUCTO]] -> 6000
A68: A062 | B68: =IFERROR(VLOOKUP(INVENTARIO[[#This Row],[CODIGO]],BASEDEDATOS[],2,FALSE),"NO EXISTE") -> DESODRANTE AMBIENTAL POETT MORADO | C68: =IFERROR(VLOOKUP(INVENTARIO[[#This Row],[CODIGO]],BASEDEDATOS[],3,FALSE),"NO EXISTE") -> AMBIENTADORES | D68: 12 | E68: 7 | F68: =INVENTARIO[[#This Row],[COMPRAS]]-INVENTARIO[[#This Row],[VENTAS]] -> 5 | H68: 2000 | I68: =INVENTARIO[[#This Row],[PRECIO DE VENTA]]-INVENTARIO[[#This Row],[COSTO UNITARIO]] -> 2000 | J68: =INVENTARIO[[#This Row],[COSTO UNITARIO]]*INVENTARIO[[#This Row],[STOCK]] -> 0 | K68: =+INVENTARIO[[#This Row],[VENTAS]]*INVENTARIO[[#This Row],[UTILIDAD POR PRODUCTO]] -> 14000
A69: A063 | B69: =IFERROR(VLOOKUP(INVENTARIO[[#This Row],[CODIGO]],BASEDEDATOS[],2,FALSE),"NO EXISTE") -> DESODRANTE EN BARRA DE HOMBRE (NIVEA) | C69: =IFERROR(VLOOKUP(INVENTARIO[[#This Row],[CODIGO]],BASEDEDATOS[],3,FALSE),"NO EXISTE") -> HIGIENE PERSONAL | D69: 15 | E69: 2 | F69: =INVENTARIO[[#This Row],[COMPRAS]]-INVENTARIO[[#This Row],[VENTAS]] -> 13 | H69: 2300 | I69: =INVENTARIO[[#This Row],[PRECIO DE VENTA]]-INVENTARIO[[#This Row],[COSTO UNITARIO]] -> 2300 | J69: =INVENTARIO[[#This Row],[COSTO UNITARIO]]*INVENTARIO[[#This Row],[STOCK]] -> 0 | K69: =+INVENTARIO[[#This Row],[VENTAS]]*INVENTARIO[[#This Row],[UTILIDAD POR PRODUCTO]] -> 4600
A70: A064 | B70: =IFERROR(VLOOKUP(INVENTARIO[[#This Row],[CODIGO]],BASEDEDATOS[],2,FALSE),"NO EXISTE") -> DESODRANTE EN SPRIE DE MUJER (DOVE) | C70: =IFERROR(VLOOKUP(INVENTARIO[[#This Row],[CODIGO]],BASEDEDATOS[],3,FALSE),"NO EXISTE") -> HIGIENE PERSONAL | D70: 6 | E70: 4 | F70: =INVENTARIO[[#This Row],[COMPRAS]]-INVENTARIO[[#This Row],[VENTAS]] -> 2 | H70: 2300 | I70: =INVENTARIO[[#This Row],[PRECIO DE VENTA]]-INVENTARIO[[#This Row],[COSTO UNITARIO]] -> 2300 | J70: =INVENTARIO[[#This Row],[COSTO UNITARIO]]*INVENTARIO[[#This Row],[STOCK]] -> 0 | K70: =+INVENTARIO[[#This Row],[VENTAS]]*INVENTARIO[[#This Row],[UTILIDAD POR PRODUCTO]] -> 9200
A71: A065 | B71: =IFERROR(VLOOKUP(INVENTARIO[[#This Row],[CODIGO]],BASEDEDATOS[],2,FALSE),"NO EXISTE") -> TOALLITAS HUMEDAS | C71: =IFERROR(VLOOKUP(INVENTARIO[[#This Row],[CODIGO]],BASEDEDATOS[],3,FALSE),"NO EXISTE") -> HIGIENE PERSONAL | D71: 40 | E71: 22 | F71: =INVENTARIO[[#This Row],[COMPRAS]]-INVENTARIO[[#This Row],[VENTAS]] -> 18 | G71: 550 | H71: 1000 | I71: =INVENTARIO[[#This Row],[PRECIO DE VENTA]]-INVENTARIO[[#This Row],[COSTO UNITARIO]] -> 450 | J71: =INVENTARIO[[#This Row],[COSTO UNITARIO]]*INVENTARIO[[#This Row],[STOCK]] -> 9900 | K71: =+INVENTARIO[[#This Row],[VENTAS]]*INVENTARIO[[#This Row],[UTILIDAD POR PRODUCTO]] -> 9900
A72: A066 | B72: =IFERROR(VLOOKUP(INVENTARIO[[#This Row],[CODIGO]],BASEDEDATOS[],2,FALSE),"NO EXISTE") -> TOALLITAS HIGIENICAS (14 UNID) | C72: =IFERROR(VLOOKUP(INVENTARIO[[#This Row],[CODIGO]],BASEDEDATOS[],3,FALSE),"NO EXISTE") -> HIGIENE PERSONAL | D72: 6 | E72: {=SUM(SUMIF(VENTAS[CODIGO],INVENTARIO!A71:A74,VENTAS[CANTIDAD]))} -> 0 | F72: =INVENTARIO[[#This Row],[COMPRAS]]-INVENTARIO[[#This Row],[VENTAS]] -> 6 | I72: =INVENTARIO[[#This Row],[PRECIO DE VENTA]]-INVENTARIO[[#This Row],[COSTO UNITARIO]] -> 0 | J72: =INVENTARIO[[#This Row],[COSTO UNITARIO]]*INVENTARIO[[#This Row],[STOCK]] -> 0 | K72: =+INVENTARIO[[#This Row],[VENTAS]]*INVENTARIO[[#This Row],[UTILIDAD POR PRODUCTO]] -> 0
A73: A067 | B73: =IFERROR(VLOOKUP(INVENTARIO[[#This Row],[CODIGO]],BASEDEDATOS[],2,FALSE),"NO EXISTE") -> PAÑUELOS DESECHABLES | C73: =IFERROR(VLOOKUP(INVENTARIO[[#This Row],[CODIGO]],BASEDEDATOS[],3,FALSE),"NO EXISTE") -> HIGIENE PERSONAL | D73: 36 | E73: 7 | F73: =INVENTARIO[[#This Row],[COMPRAS]]-INVENTARIO[[#This Row],[VENTAS]] -> 29 | I73: =INVENTARIO[[#This Row],[PRECIO DE VENTA]]-INVENTARIO[[#This Row],[COSTO UNITARIO]] -> 0 | J73: =INVENTARIO[[#This Row],[COSTO UNITARIO]]*INVENTARIO[[#This Row],[STOCK]] -> 0 | K73: =+INVENTARIO[[#This Row],[VENTAS]]*INVENTARIO[[#This Row],[UTILIDAD POR PRODUCTO]] -> 0
A74: A068 | B74: =IFERROR(VLOOKUP(INVENTARIO[[#This Row],[CODIGO]],BASEDEDATOS[],2,FALSE),"NO EXISTE") -> JABON EN BARRA (WINEX) | C74: =IFERROR(VLOOKUP(INVENTARIO[[#This Row],[CODIGO]],BASEDEDATOS[],3,FALSE),"NO EXISTE") -> HIGIENE PERSONAL | D74: 24 | E74: 0 | F74: =INVENTARIO[[#This Row],[COMPRAS]]-INVENTARIO[[#This Row],[VENTAS]] -> 24 | H74: 1500 | I74: =INVENTARIO[[#This Row],[PRECIO DE VENTA]]-INVENTARIO[[#This Row],[COSTO UNITARIO]] -> 1500 | J74: =INVENTARIO[[#This Row],[COSTO UNITARIO]]*INVENTARIO[[#This Row],[STOCK]] -> 0 | K74: =+INVENTARIO[[#This Row],[VENTAS]]*INVENTARIO[[#This Row],[UTILIDAD POR PRODUCTO]] -> 0
A75: A069 | B75: =IFERROR(VLOOKUP(INVENTARIO[[#This Row],[CODIGO]],BASEDEDATOS[],2,FALSE),"NO EXISTE") -> JABON LIQUIDO COLOR NARANJO | C75: =IFERROR(VLOOKUP(INVENTARIO[[#This Row],[CODIGO]],BASEDEDATOS[],3,FALSE),"NO EXISTE") -> HIGIENE PERSONAL | D75: 12 | E75: {=SUM(SUMIF(VENTAS[CODIGO],INVENTARIO!A74:A77,VENTAS[CANTIDAD]))} -> 0 | F75: =INVENTARIO[[#This Row],[COMPRAS]]-INVENTARIO[[#This Row],[VENTAS]] -> 12 | G75: 990 | H75: 1400 | I75: =INVENTARIO[[#This Row],[PRECIO DE VENTA]]-INVENTARIO[[#This Row],[COSTO UNITARIO]] -> 410 | J75: =INVENTARIO[[#This Row],[COSTO UNITARIO]]*INVENTARIO[[#This Row],[STOCK]] -> 11880 | K75: =+INVENTARIO[[#This Row],[VENTAS]]*INVENTARIO[[#This Row],[UTILIDAD POR PRODUCTO]] -> 0
A76: A070 | B76: =IFERROR(VLOOKUP(INVENTARIO[[#This Row],[CODIGO]],BASEDEDATOS[],2,FALSE),"NO EXISTE") -> JABON LIQUIDO COLOR ROSADO | C76: =IFERROR(VLOOKUP(INVENTARIO[[#This Row],[CODIGO]],BASEDEDATOS[],3,FALSE),"NO EXISTE") -> HIGIENE PERSONAL | D76: 12 | E76: 4 | F76: =INVENTARIO[[#This Row],[COMPRAS]]-INVENTARIO[[#This Row],[VENTAS]] -> 8 | G76: 990 | H76: 1400 | I76: =INVENTARIO[[#This Row],[PRECIO DE VENTA]]-INVENTARIO[[#This Row],[COSTO UNITARIO]] -> 410 | J76: =INVENTARIO[[#This Row],[COSTO UNITARIO]]*INVENTARIO[[#This Row],[STOCK]] -> 7920 | K76: =+INVENTARIO[[#This Row],[VENTAS]]*INVENTARIO[[#This Row],[UTILIDAD POR PRODUCTO]] -> 1640
A77: A071 | B77: =IFERROR(VLOOKUP(INVENTARIO[[#This Row],[CODIGO]],BASEDEDATOS[],2,FALSE),"NO EXISTE") -> JABON LIQUIDO COLOR CELESTE | C77: =IFERROR(VLOOKUP(INVENTARIO[[#This Row],[CODIGO]],BASEDEDATOS[],3,FALSE),"NO EXISTE") -> HIGIENE PERSONAL | D77: 12 | E77: 6 | F77: =INVENTARIO[[#This Row],[COMPRAS]]-INVENTARIO[[#This Row],[VENTAS]] -> 6 | G77: 990 | H77: 1400 | I77: =INVENTARIO[[#This Row],[PRECIO DE VENTA]]-INVENTARIO[[#This Row],[COSTO UNITARIO]] -> 410 | J77: =INVENTARIO[[#This Row],[COSTO UNITARIO]]*INVENTARIO[[#This Row],[STOCK]] -> 5940 | K77: =+INVENTARIO[[#This Row],[VENTAS]]*INVENTARIO[[#This Row],[UTILIDAD POR PRODUCTO]] -> 2460
A78: A072 | B78: =IFERROR(VLOOKUP(INVENTARIO[[#This Row],[CODIGO]],BASEDEDATOS[],2,FALSE),"NO EXISTE") -> JABON LIQUIDO DOVE | C78: =IFERROR(VLOOKUP(INVENTARIO[[#This Row],[CODIGO]],BASEDEDATOS[],3,FALSE),"NO EXISTE") -> HIGIENE PERSONAL | D78: {=SUMPRODUCT(SUMIF(COMPRAS[CODIGO],INVENTARIO!A77:A79,COMPRAS[CANTIDAD]))} -> 0 | E78: {=SUM(SUMIF(VENTAS[CODIGO],INVENTARIO!A77:A80,VENTAS[CANTIDAD]))} -> 0 | F78: =INVENTARIO[[#This Row],[COMPRAS]]-INVENTARIO[[#This Row],[VENTAS]] -> 0 | I78: =INVENTARIO[[#This Row],[PRECIO DE VENTA]]-INVENTARIO[[#This Row],[COSTO UNITARIO]] -> 0 | J78: =INVENTARIO[[#This Row],[COSTO UNITARIO]]*INVENTARIO[[#This Row],[STOCK]] -> 0 | K78: =+INVENTARIO[[#This Row],[VENTAS]]*INVENTARIO[[#This Row],[UTILIDAD POR PRODUCTO]] -> 0
A79: A073 | B79: =IFERROR(VLOOKUP(INVENTARIO[[#This Row],[CODIGO]],BASEDEDATOS[],2,FALSE),"NO EXISTE") -> JABON EN BARRA DOVE | C79: =IFERROR(VLOOKUP(INVENTARIO[[#This Row],[CODIGO]],BASEDEDATOS[],3,FALSE),"NO EXISTE") -> HIGIENE PERSONAL | D79: 6 | E79: 5 | F79: =INVENTARIO[[#This Row],[COMPRAS]]-INVENTARIO[[#This Row],[VENTAS]] -> 1 | G79: 890 | H79: 1100 | I79: =INVENTARIO[[#This Row],[PRECIO DE VENTA]]-INVENTARIO[[#This Row],[COSTO UNITARIO]] -> 210 | J79: =INVENTARIO[[#This Row],[COSTO UNITARIO]]*INVENTARIO[[#This Row],[STOCK]] -> 890 | K79: =+INVENTARIO[[#This Row],[VENTAS]]*INVENTARIO[[#This Row],[UTILIDAD POR PRODUCTO]] -> 1050
A80: A074 | B80: =IFERROR(VLOOKUP(INVENTARIO[[#This Row],[CODIGO]],BASEDEDATOS[],2,FALSE),"NO EXISTE") -> PAPEL HIGIENICO SCOTT 50 MTS | C80: =IFERROR(VLOOKUP(INVENTARIO[[#This Row],[CODIGO]],BASEDEDATOS[],3,FALSE),"NO EXISTE") -> HIGIENE PERSONAL | D80: {=SUMPRODUCT(SUMIF(COMPRAS[CODIGO],INVENTARIO!A79:A81,COMPRAS[CANTIDAD]))} -> 0 | E80: {=SUM(SUMIF(VENTAS[CODIGO],INVENTARIO!A79:A82,VENTAS[CANTIDAD]))} -> 0 | F80: =INVENTARIO[[#This Row],[COMPRAS]]-INVENTARIO[[#This Row],[VENTAS]] -> 0 | I80: =INVENTARIO[[#This Row],[PRECIO DE VENTA]]-INVENTARIO[[#This Row],[COSTO UNITARIO]] -> 0 | J80: =INVENTARIO[[#This Row],[COSTO UNITARIO]]*INVENTARIO[[#This Row],[STOCK]] -> 0 | K80: =+INVENTARIO[[#This Row],[VENTAS]]*INVENTARIO[[#This Row],[UTILIDAD POR PRODUCTO]] -> 0
A81: A075 | B81: =IFERROR(VLOOKUP(INVENTARIO[[#This Row],[CODIGO]],BASEDEDATOS[],2,FALSE),"NO EXISTE") -> PAPEL HIGIENICO ECONOMICO 23 MTS | C81: =IFERROR(VLOOKUP(INVENTARIO[[#This Row],[CODIGO]],BASEDEDATOS[],3,FALSE),"NO EXISTE") -> HIGIENE PERSONAL | D81: {=SUMPRODUCT(SUMIF(COMPRAS[CODIGO],INVENTARIO!A80:A82,COMPRAS[CANTIDAD]))} -> 0 | E81: {=SUM(SUMIF(VENTAS[CODIGO],INVENTARIO!A80:A83,VENTAS[CANTIDAD]))} -> 0 | F81: =INVENTARIO[[#This Row],[COMPRAS]]-INVENTARIO[[#This Row],[VENTAS]] -> 0 | I81: =INVENTARIO[[#This Row],[PRECIO DE VENTA]]-INVENTARIO[[#This Row],[COSTO UNITARIO]] -> 0 | J81: =INVENTARIO[[#This Row],[COSTO UNITARIO]]*INVENTARIO[[#This Row],[STOCK]] -> 0 | K81: =+INVENTARIO[[#This Row],[VENTAS]]*INVENTARIO[[#This Row],[UTILIDAD POR PRODUCTO]] -> 0
A82: A076 | B82: =IFERROR(VLOOKUP(INVENTARIO[[#This Row],[CODIGO]],BASEDEDATOS[],2,FALSE),"NO EXISTE") -> PAPEL HIGIENICO NOBLE 23 MTS | C82: =IFERROR(VLOOKUP(INVENTARIO[[#This Row],[CODIGO]],BASEDEDATOS[],3,FALSE),"NO EXISTE") -> HIGIENE PERSONAL | D82: =24*7 -> 168 | E82: 24 | F82: =INVENTARIO[[#This Row],[COMPRAS]]-INVENTARIO[[#This Row],[VENTAS]] -> 144 | H82: 1400 | I82: =INVENTARIO[[#This Row],[PRECIO DE VENTA]]-INVENTARIO[[#This Row],[COSTO UNITARIO]] -> 1400 | J82: =INVENTARIO[[#This Row],[COSTO UNITARIO]]*INVENTARIO[[#This Row],[STOCK]] -> 0 | K82: =+INVENTARIO[[#This Row],[VENTAS]]*INVENTARIO[[#This Row],[UTILIDAD POR PRODUCTO]] -> 33600
A83: A077 | B83: =IFERROR(VLOOKUP(INVENTARIO[[#This Row],[CODIGO]],BASEDEDATOS[],2,FALSE),"NO EXISTE") -> SERVILLETAS SUAN | C83: =IFERROR(VLOOKUP(INVENTARIO[[#This Row],[CODIGO]],BASEDEDATOS[],3,FALSE),"NO EXISTE") -> HIGIENE PERSONAL | D83: 12 | E83: {=SUM(SUMIF(VENTAS[CODIGO],INVENTARIO!A82:A85,VENTAS[CANTIDAD]))} -> 0 | F83: =INVENTARIO[[#This Row],[COMPRAS]]-INVENTARIO[[#This Row],[VENTAS]] -> 12 | H83: 1500 | I83: =INVENTARIO[[#This Row],[PRECIO DE VENTA]]-INVENTARIO[[#This Row],[COSTO UNITARIO]] -> 1500 | J83: =INVENTARIO[[#This Row],[COSTO UNITARIO]]*INVENTARIO[[#This Row],[STOCK]] -> 0 | K83: =+INVENTARIO[[#This Row],[VENTAS]]*INVENTARIO[[#This Row],[UTILIDAD POR PRODUCTO]] -> 0
A84: A078 | B84: =IFERROR(VLOOKUP(INVENTARIO[[#This Row],[CODIGO]],BASEDEDATOS[],2,FALSE),"NO EXISTE") -> TOALLA NOVA ABOLENGO | C84: =IFERROR(VLOOKUP(INVENTARIO[[#This Row],[CODIGO]],BASEDEDATOS[],3,FALSE),"NO EXISTE") -> HIGIENE PERSONAL | D84: 24 | E84: {=SUM(SUMIF(VENTAS[CODIGO],INVENTARIO!A83:A86,VENTAS[CANTIDAD]))} -> 0 | F84: =INVENTARIO[[#This Row],[COMPRAS]]-INVENTARIO[[#This Row],[VENTAS]] -> 24 | H84: 1300 | I84: =INVENTARIO[[#This Row],[PRECIO DE VENTA]]-INVENTARIO[[#This Row],[COSTO UNITARIO]] -> 1300 | J84: =INVENTARIO[[#This Row],[COSTO UNITARIO]]*INVENTARIO[[#This Row],[STOCK]] -> 0 | K84: =+INVENTARIO[[#This Row],[VENTAS]]*INVENTARIO[[#This Row],[UTILIDAD POR PRODUCTO]] -> 0
A85: A079 | B85: =IFERROR(VLOOKUP(INVENTARIO[[#This Row],[CODIGO]],BASEDEDATOS[],2,FALSE),"NO EXISTE") -> TOALLA NOVA SUAN | C85: =IFERROR(VLOOKUP(INVENTARIO[[#This Row],[CODIGO]],BASEDEDATOS[],3,FALSE),"NO EXISTE") -> HIGIENE PERSONAL | D85: 24 | E85: {=SUM(SUMIF(VENTAS[CODIGO],INVENTARIO!A84:A87,VENTAS[CANTIDAD]))} -> 0 | F85: =INVENTARIO[[#This Row],[COMPRAS]]-INVENTARIO[[#This Row],[VENTAS]] -> 24 | H85: 1500 | I85: =INVENTARIO[[#This Row],[PRECIO DE VENTA]]-INVENTARIO[[#This Row],[COSTO UNITARIO]] -> 1500 | J85: =INVENTARIO[[#This Row],[COSTO UNITARIO]]*INVENTARIO[[#This Row],[STOCK]] -> 0 | K85: =+INVENTARIO[[#This Row],[VENTAS]]*INVENTARIO[[#This Row],[UTILIDAD POR PRODUCTO]] -> 0
A86: A080 | B86: =IFERROR(VLOOKUP(INVENTARIO[[#This Row],[CODIGO]],BASEDEDATOS[],2,FALSE),"NO EXISTE") -> TOALLA NOVA | C86: =IFERROR(VLOOKUP(INVENTARIO[[#This Row],[CODIGO]],BASEDEDATOS[],3,FALSE),"NO EXISTE") -> HIGIENE PERSONAL | D86: 24 | E86: {=SUM(SUMIF(VENTAS[CODIGO],INVENTARIO!A85:A88,VENTAS[CANTIDAD]))} -> 0 | F86: =INVENTARIO[[#This Row],[COMPRAS]]-INVENTARIO[[#This Row],[VENTAS]] -> 24 | H86: 1500 | I86: =INVENTARIO[[#This Row],[PRECIO DE VENTA]]-INVENTARIO[[#This Row],[COSTO UNITARIO]] -> 1500 | J86: =INVENTARIO[[#This Row],[COSTO UNITARIO]]*INVENTARIO[[#This Row],[STOCK]] -> 0 | K86: =+INVENTARIO[[#This Row],[VENTAS]]*INVENTARIO[[#This Row],[UTILIDAD POR PRODUCTO]] -> 0
A87: A081 | B87: =IFERROR(VLOOKUP(INVENTARIO[[#This Row],[CODIGO]],BASEDEDATOS[],2,FALSE),"NO EXISTE") -> TOALLA NOVA 70 MTS | C87: =IFERROR(VLOOKUP(INVENTARIO[[#This Row],[CODIGO]],BASEDEDATOS[],3,FALSE),"NO EXISTE") -> HIGIENE PERSONAL | D87: 16 | E87: 12 | F87: =INVENTARIO[[#This Row],[COMPRAS]]-INVENTARIO[[#This Row],[VENTAS]] -> 4 | G87: 1749 | H87: 3000 | I87: =INVENTARIO[[#This Row],[PRECIO DE VENTA]]-INVENTARIO[[#This Row],[COSTO UNITARIO]] -> 1251 | J87: =INVENTARIO[[#This Row],[COSTO UNITARIO]]*INVENTARIO[[#This Row],[STOCK]] -> 6996 | K87: =+INVENTARIO[[#This Row],[VENTAS]]*INVENTARIO[[#This Row],[UTILIDAD POR PRODUCTO]] -> 15012
A88: A082 | B88: =IFERROR(VLOOKUP(INVENTARIO[[#This Row],[CODIGO]],BASEDEDATOS[],2,FALSE),"NO EXISTE") -> CEPILLO DE DIENTES | C88: =IFERROR(VLOOKUP(INVENTARIO[[#This Row],[CODIGO]],BASEDEDATOS[],3,FALSE),"NO EXISTE") -> HIGIENE PERSONAL | D88: {=SUMPRODUCT(SUMIF(COMPRAS[CODIGO],INVENTARIO!A87:A89,COMPRAS[CANTIDAD]))} -> 0 | E88: {=SUM(SUMIF(VENTAS[CODIGO],INVENTARIO!A87:A90,VENTAS[CANTIDAD]))} -> 0 | F88: =INVENTARIO[[#This Row],[COMPRAS]]-INVENTARIO[[#This Row],[VENTAS]] -> 0 | I88: =INVENTARIO[[#This Row],[PRECIO DE VENTA]]-INVENTARIO[[#This Row],[COSTO UNITARIO]] -> 0 | J88: =INVENTARIO[[#This Row],[COSTO UNITARIO]]*INVENTARIO[[#This Row],[STOCK]] -> 0 | K88: =+INVENTARIO[[#This Row],[VENTAS]]*INVENTARIO[[#This Row],[UTILIDAD POR PRODUCTO]] -> 0
A89: A083 | B89: =IFERROR(VLOOKUP(INVENTARIO[[#This Row],[CODIGO]],BASEDEDATOS[],2,FALSE),"NO EXISTE") -> PASTA DE DIENTES AQUAFRESH | C89: =IFERROR(VLOOKUP(INVENTARIO[[#This Row],[CODIGO]],BASEDEDATOS[],3,FALSE),"NO EXISTE") -> HIGIENE PERSONAL | D89: {=SUMPRODUCT(SUMIF(COMPRAS[CODIGO],INVENTARIO!A88:A90,COMPRAS[CANTIDAD]))} -> 0 | E89: {=SUM(SUMIF(VENTAS[CODIGO],INVENTARIO!A88:A91,VENTAS[CANTIDAD]))} -> 0 | F89: =INVENTARIO[[#This Row],[COMPRAS]]-INVENTARIO[[#This Row],[VENTAS]] -> 0 | I89: =INVENTARIO[[#This Row],[PRECIO DE VENTA]]-INVENTARIO[[#This Row],[COSTO UNITARIO]] -> 0 | J89: =INVENTARIO[[#This Row],[COSTO UNITARIO]]*INVENTARIO[[#This Row],[STOCK]] -> 0 | K89: =+INVENTARIO[[#This Row],[VENTAS]]*INVENTARIO[[#This Row],[UTILIDAD POR PRODUCTO]] -> 0
A90: A084 | B90: =IFERROR(VLOOKUP(INVENTARIO[[#This Row],[CODIGO]],BASEDEDATOS[],2,FALSE),"NO EXISTE") -> PASTA DE DIENTES COLGATE | C90: =IFERROR(VLOOKUP(INVENTARIO[[#This Row],[CODIGO]],BASEDEDATOS[],3,FALSE),"NO EXISTE") -> HIGIENE PERSONAL | D90: 12 | E90: 12 | F90: =INVENTARIO[[#This Row],[COMPRAS]]-INVENTARIO[[#This Row],[VENTAS]] -> 0 | I90: =INVENTARIO[[#This Row],[PRECIO DE VENTA]]-INVENTARIO[[#This Row],[COSTO UNITARIO]] -> 0 | J90: =INVENTARIO[[#This Row],[COSTO UNITARIO]]*INVENTARIO[[#This Row],[STOCK]] -> 0 | K90: =+INVENTARIO[[#This Row],[VENTAS]]*INVENTARIO[[#This Row],[UTILIDAD POR PRODUCTO]] -> 0
A91: A085 | B91: =IFERROR(VLOOKUP(INVENTARIO[[#This Row],[CODIGO]],BASEDEDATOS[],2,FALSE),"NO EXISTE") -> PRESTO BARBA DE HOMBRE GILLETTE 3 | C91: =IFERROR(VLOOKUP(INVENTARIO[[#This Row],[CODIGO]],BASEDEDATOS[],3,FALSE),"NO EXISTE") -> HIGIENE PERSONAL | D91: 12 | E91: 11 | F91: =INVENTARIO[[#This Row],[COMPRAS]]-INVENTARIO[[#This Row],[VENTAS]] -> 1 | I91: =INVENTARIO[[#This Row],[PRECIO DE VENTA]]-INVENTARIO[[#This Row],[COSTO UNITARIO]] -> 0 | J91: =INVENTARIO[[#This Row],[COSTO UNITARIO]]*INVENTARIO[[#This Row],[STOCK]] -> 0 | K91: =+INVENTARIO[[#This Row],[VENTAS]]*INVENTARIO[[#This Row],[UTILIDAD POR PRODUCTO]] -> 0
A92: A086 | B92: =IFERROR(VLOOKUP(INVENTARIO[[#This Row],[CODIGO]],BASEDEDATOS[],2,FALSE),"NO EXISTE") -> PRESTO BARBA DE HOMBRE SCHICK | C92: =IFERROR(VLOOKUP(INVENTARIO[[#This Row],[CODIGO]],BASEDEDATOS[],3,FALSE),"NO EXISTE") -> HIGIENE PERSONAL | D92: 23 | E92: {=SUM(SUMIF(VENTAS[CODIGO],INVENTARIO!A91:A94,VENTAS[CANTIDAD]))} -> 0 | F92: =INVENTARIO[[#This Row],[COMPRAS]]-INVENTARIO[[#This Row],[VENTAS]] -> 23 | G92: 720 | H92: 1000 | I92: =INVENTARIO[[#This Row],[PRECIO DE VENTA]]-INVENTARIO[[#This Row],[COSTO UNITARIO]] -> 280 | J92: =INVENTARIO[[#This Row],[COSTO UNITARIO]]*INVENTARIO[[#This Row],[STOCK]] -> 16560 | K92: =+INVENTARIO[[#This Row],[VENTAS]]*INVENTARIO[[#This Row],[UTILIDAD POR PRODUCTO]] -> 0
A93: A087 | B93: =IFERROR(VLOOKUP(INVENTARIO[[#This Row],[CODIGO]],BASEDEDATOS[],2,FALSE),"NO EXISTE") -> PRESTO BARBA DE HOMBRE WILKINSON | C93: =IFERROR(VLOOKUP(INVENTARIO[[#This Row],[CODIGO]],BASEDEDATOS[],3,FALSE),"NO EXISTE") -> HIGIENE PERSONAL | D93: {=SUMPRODUCT(SUMIF(COMPRAS[CODIGO],INVENTARIO!A92:A94,COMPRAS[CANTIDAD]))} -> 0 | E93: {=SUM(SUMIF(VENTAS[CODIGO],INVENTARIO!A92:A95,VENTAS[CANTIDAD]))} -> 0 | F93: =INVENTARIO[[#This Row],[COMPRAS]]-INVENTARIO[[#This Row],[VENTAS]] -> 0 | I93: =INVENTARIO[[#This Row],[PRECIO DE VENTA]]-INVENTARIO[[#This Row],[COSTO UNITARIO]] -> 0 | J93: =INVENTARIO[[#This Row],[COSTO UNITARIO]]*INVENTARIO[[#This Row],[STOCK]] -> 0 | K93: =+INVENTARIO[[#This Row],[VENTAS]]*INVENTARIO[[#This Row],[UTILIDAD POR PRODUCTO]] -> 0
A94: A088 | B94: =IFERROR(VLOOKUP(INVENTARIO[[#This Row],[CODIGO]],BASEDEDATOS[],2,FALSE),"NO EXISTE") -> PRESTO BARBA DE MUJER SCHICK | C94: =IFERROR(VLOOKUP(INVENTARIO[[#This Row],[CODIGO]],BASEDEDATOS[],3,FALSE),"NO EXISTE") -> HIGIENE PERSONAL | D94: 22 | E94: {=SUM(SUMIF(VENTAS[CODIGO],INVENTARIO!A93:A96,VENTAS[CANTIDAD]))} -> 0 | F94: =INVENTARIO[[#This Row],[COMPRAS]]-INVENTARIO[[#This Row],[VENTAS]] -> 22 | G94: 759 | H94: 1000 | I94: =INVENTARIO[[#This Row],[PRECIO DE VENTA]]-INVENTARIO[[#This Row],[COSTO UNITARIO]] -> 241 | J94: =INVENTARIO[[#This Row],[COSTO UNITARIO]]*INVENTARIO[[#This Row],[STOCK]] -> 16698 | K94: =+INVENTARIO[[#This Row],[VENTAS]]*INVENTARIO[[#This Row],[UTILIDAD POR PRODUCTO]] -> 0
A95: A089 | B95: =IFERROR(VLOOKUP(INVENTARIO[[#This Row],[CODIGO]],BASEDEDATOS[],2,FALSE),"NO EXISTE") -> PRESTO BARBA DE MUJER VENUS | C95: =IFERROR(VLOOKUP(INVENTARIO[[#This Row],[CODIGO]],BASEDEDATOS[],3,FALSE),"NO EXISTE") -> HIGIENE PERSONAL | D95: {=SUMPRODUCT(SUMIF(COMPRAS[CODIGO],INVENTARIO!A94:A96,COMPRAS[CANTIDAD]))} -> 0 | E95: {=SUM(SUMIF(VENTAS[CODIGO],INVENTARIO!A94:A97,VENTAS[CANTIDAD]))} -> 0 | F95: =INVENTARIO[[#This Row],[COMPRAS]]-INVENTARIO[[#This Row],[VENTAS]] -> 0 | I95: =INVENTARIO[[#This Row],[PRECIO DE VENTA]]-INVENTARIO[[#This Row],[COSTO UNITARIO]] -> 0 | J95: =INVENTARIO[[#This Row],[COSTO UNITARIO]]*INVENTARIO[[#This Row],[STOCK]] -> 0 | K95: =+INVENTARIO[[#This Row],[VENTAS]]*INVENTARIO[[#This Row],[UTILIDAD POR PRODUCTO]] -> 0
A96: A090 | B96: =IFERROR(VLOOKUP(INVENTARIO[[#This Row],[CODIGO]],BASEDEDATOS[],2,FALSE),"NO EXISTE") -> COTONITOS | C96: =IFERROR(VLOOKUP(INVENTARIO[[#This Row],[CODIGO]],BASEDEDATOS[],3,FALSE),"NO EXISTE") -> HIGIENE PERSONAL | D96: 12 | E96: 2 | F96: =INVENTARIO[[#This Row],[COMPRAS]]-INVENTARIO[[#This Row],[VENTAS]] -> 10 | G96: 250 | H96: 500 | I96: =INVENTARIO[[#This Row],[PRECIO DE VENTA]]-INVENTARIO[[#This Row],[COSTO UNITARIO]] -> 250 | J96: =INVENTARIO[[#This Row],[COSTO UNITARIO]]*INVENTARIO[[#This Row],[STOCK]] -> 2500 | K96: =+INVENTARIO[[#This Row],[VENTAS]]*INVENTARIO[[#This Row],[UTILIDAD POR PRODUCTO]] -> 500
A97: A091 | B97: =IFERROR(VLOOKUP(INVENTARIO[[#This Row],[CODIGO]],BASEDEDATOS[],2,FALSE),"NO EXISTE") -> QUITAESMALTE | C97: =IFERROR(VLOOKUP(INVENTARIO[[#This Row],[CODIGO]],BASEDEDATOS[],3,FALSE),"NO EXISTE") -> HIGIENE PERSONAL | D97: 6 | E97: 2 | F97: 4 | G97: 790 | H97: 1000 | I97: =INVENTARIO[[#This Row],[PRECIO DE VENTA]]-INVENTARIO[[#This Row],[COSTO UNITARIO]] -> 210 | J97: =INVENTARIO[[#This Row],[COSTO UNITARIO]]*INVENTARIO[[#This Row],[STOCK]] -> 3160 | K97: =+INVENTARIO[[#This Row],[VENTAS]]*INVENTARIO[[#This Row],[UTILIDAD POR PRODUCTO]] -> 420
A98: A092 | B98: =IFERROR(VLOOKUP(INVENTARIO[[#This Row],[CODIGO]],BASEDEDATOS[],2,FALSE),"NO EXISTE") -> SHAMPOO VALLERINA AROMA GRANADA | C98: =IFERROR(VLOOKUP(INVENTARIO[[#This Row],[CODIGO]],BASEDEDATOS[],3,FALSE),"NO EXISTE") -> HIGIENE PERSONAL | D98: 12 | E98: 6 | F98: =INVENTARIO[[#This Row],[COMPRAS]]-INVENTARIO[[#This Row],[VENTAS]] -> 6 | H98: 1400 | I98: =INVENTARIO[[#This Row],[PRECIO DE VENTA]]-INVENTARIO[[#This Row],[COSTO UNITARIO]] -> 1400 | J98: =INVENTARIO[[#This Row],[COSTO UNITARIO]]*INVENTARIO[[#This Row],[STOCK]] -> 0 | K98: =+INVENTARIO[[#This Row],[VENTAS]]*INVENTARIO[[#This Row],[UTILIDAD POR PRODUCTO]] -> 8400
A99: A093 | B99: =IFERROR(VLOOKUP(INVENTARIO[[#This Row],[CODIGO]],BASEDEDATOS[],2,FALSE),"NO EXISTE") -> SHAMPOO VALLERINA AROMA GRANADA | C99: =IFERROR(VLOOKUP(INVENTARIO[[#This Row],[CODIGO]],BASEDEDATOS[],3,FALSE),"NO EXISTE") -> HIGIENE PERSONAL | D99: 12 | E99: 4 | F99: =INVENTARIO[[#This Row],[COMPRAS]]-INVENTARIO[[#This Row],[VENTAS]] -> 8 | H99: 1400 | I99: =INVENTARIO[[#This Row],[PRECIO DE VENTA]]-INVENTARIO[[#This Row],[COSTO UNITARIO]] -> 1400 | J99: =INVENTARIO[[#This Row],[COSTO UNITARIO]]*INVENTARIO[[#This Row],[STOCK]] -> 0 | K99: =+INVENTARIO[[#This Row],[VENTAS]]*INVENTARIO[[#This Row],[UTILIDAD POR PRODUCTO]] -> 5600
A100: A094 | B100: =IFERROR(VLOOKUP(INVENTARIO[[#This Row],[CODIGO]],BASEDEDATOS[],2,FALSE),"NO EXISTE") -> SHAMPOO DOVE | C100: =IFERROR(VLOOKUP(INVENTARIO[[#This Row],[CODIGO]],BASEDEDATOS[],3,FALSE),"NO EXISTE") -> HIGIENE PERSONAL | D100: 6 | E100: 2 | F100: =INVENTARIO[[#This Row],[COMPRAS]]-INVENTARIO[[#This Row],[VENTAS]] -> 4 | G100: 1504 | H100: 2500 | I100: =INVENTARIO[[#This Row],[PRECIO DE VENTA]]-INVENTARIO[[#This Row],[COSTO UNITARIO]] -> 996 | J100: =INVENTARIO[[#This Row],[COSTO UNITARIO]]*INVENTARIO[[#This Row],[STOCK]] -> 6016 | K100: =+INVENTARIO[[#This Row],[VENTAS]]*INVENTARIO[[#This Row],[UTILIDAD POR PRODUCTO]] -> 1992
A101: A095 | B101: =IFERROR(VLOOKUP(INVENTARIO[[#This Row],[CODIGO]],BASEDEDATOS[],2,FALSE),"NO EXISTE") -> ACONDICIONADOR DOVE | C101: =IFERROR(VLOOKUP(INVENTARIO[[#This Row],[CODIGO]],BASEDEDATOS[],3,FALSE),"NO EXISTE") -> HIGIENE PERSONAL | D101: 6 | E101: 1 | F101: =INVENTARIO[[#This Row],[COMPRAS]]-INVENTARIO[[#This Row],[VENTAS]] -> 5 | G101: 1504 | H101: 2500 | I101: =INVENTARIO[[#This Row],[PRECIO DE VENTA]]-INVENTARIO[[#This Row],[COSTO UNITARIO]] -> 996 | J101: =INVENTARIO[[#This Row],[COSTO UNITARIO]]*INVENTARIO[[#This Row],[STOCK]] -> 7520 | K101: =+INVENTARIO[[#This Row],[VENTAS]]*INVENTARIO[[#This Row],[UTILIDAD POR PRODUCTO]] -> 996
A102: A096 | B102: =IFERROR(VLOOKUP(INVENTARIO[[#This Row],[CODIGO]],BASEDEDATOS[],2,FALSE),"NO EXISTE") -> SHAMPOO FAMILAND | C102: =IFERROR(VLOOKUP(INVENTARIO[[#This Row],[CODIGO]],BASEDEDATOS[],3,FALSE),"NO EXISTE") -> HIGIENE PERSONAL | D102: 12 | E102: 6 | F102: =INVENTARIO[[#This Row],[COMPRAS]]-INVENTARIO[[#This Row],[VENTAS]] -> 6 | G102: 1190 | H102: 1800 | I102: =INVENTARIO[[#This Row],[PRECIO DE VENTA]]-INVENTARIO[[#This Row],[COSTO UNITARIO]] -> 610 | J102: =INVENTARIO[[#This Row],[COSTO UNITARIO]]*INVENTARIO[[#This Row],[STOCK]] -> 7140 | K102: =+INVENTARIO[[#This Row],[VENTAS]]*INVENTARIO[[#This Row],[UTILIDAD POR PRODUCTO]] -> 3660
...

Sheet COMPRAS
A1: COMPRAS
I4: TOTAL
I5: =SUBTOTAL(9,I7:I118) -> 973059
A6: CODIGO | B6: FECHA | C6: MES | D6: AÑO | E6: NOMBRE DEL PRODUCTO | F6: CATEGORIA | G6: COSTO UNITARIO | H6: CANTIDAD | I6: TOTAL
A7: A001 | B7: 45945 | C7: =TEXT(COMPRAS[[#This Row],[FECHA]],"[$-es-CL]mmmm") -> octubre | D7: {=YEAR(IF(ISNUMBER(COMPRAS[[#This Row],[FECHA]]),COMPRAS[[#This Row],[FECHA]],FECHA.VALOR(COMPRAS[[#This Row],[FECHA]])))} -> 2025 | E7: =IFERROR(VLOOKUP(COMPRAS[[#This Row],[CODIGO]],INVENTARIO[],2,FALSE),"NO EXISTE") -> DETERGENTE BIO AZUL DE 5 LITROS | F7: =IFERROR(VLOOKUP(COMPRAS[[#This Row],[CODIGO]],INVENTARIO[],3,FALSE),"NO EXISTE") -> LAVANDERIA | G7: 920 | H7: 150 | I7: =COMPRAS[[#This Row],[COSTO UNITARIO]]*COMPRAS[[#This Row],[CANTIDAD]] -> 138000
A8: A002 | B8: 45945 | C8: =TEXT(COMPRAS[[#This Row],[FECHA]],"[$-es-CL]mmmm") -> octubre | D8: {=YEAR(IF(ISNUMBER(COMPRAS[[#This Row],[FECHA]]),COMPRAS[[#This Row],[FECHA]],FECHA.VALOR(COMPRAS[[#This Row],[FECHA]])))} -> 2025 | E8: =IFERROR(VLOOKUP(COMPRAS[[#This Row],[CODIGO]],INVENTARIO[],2,FALSE),"NO EXISTE") -> DETERGENTE BIO VERDE DE 5 LITROS | F8: =IFERROR(VLOOKUP(COMPRAS[[#This Row],[CODIGO]],INVENTARIO[],3,FALSE),"NO EXISTE") -> LAVANDERIA | G8: 920 | H8: 50 | I8: =COMPRAS[[#This Row],[COSTO UNITARIO]]*COMPRAS[[#This Row],[CANTIDAD]] -> 46000
A9: A003 | B9: 45945 | C9: =TEXT(COMPRAS[[#This Row],[FECHA]],"[$-es-CL]mmmm") -> octubre | D9: {=YEAR(IF(ISNUMBER(COMPRAS[[#This Row],[FECHA]]),COMPRAS[[#This Row],[FECHA]],FECHA.VALOR(COMPRAS[[#This Row],[FECHA]])))} -> 2025 | E9: =IFERROR(VLOOKUP(COMPRAS[[#This Row],[CODIGO]],INVENTARIO[],2,FALSE),"NO EXISTE") -> DETERGENTE MORADO CON SUAVIZANTE DE 5 LITROS | F9: =IFERROR(VLOOKUP(COMPRAS[[#This Row],[CODIGO]],INVENTARIO[],3,FALSE),"NO EXISTE") -> LAVANDERIA | G9: 1490 | H9: 0 | I9: =COMPRAS[[#This Row],[COSTO UNITARIO]]*COMPRAS[[#This Row],[CANTIDAD]] -> 0
A10: A004 | B10: 45945 | C10: =TEXT(COMPRAS[[#This Row],[FECHA]],"[$-es-CL]mmmm") -> octubre | D10: {=YEAR(IF(ISNUMBER(COMPRAS[[#This Row],[FECHA]]),COMPRAS[[#This Row],[FECHA]],FECHA.VALOR(COMPRAS[[#This Row],[FECHA]])))} -> 2025 | E10: =IFERROR(VLOOKUP(COMPRAS[[#This Row],[CODIGO]],INVENTARIO[],2,FALSE),"NO EXISTE") -> DETERGENTE BLANCO CON SUAVIZANTE DE 5 LITROS | F10: =IFERROR(VLOOKUP(COMPRAS[[#This Row],[CODIGO]],INVENTARIO[],3,FALSE),"NO EXISTE") -> LAVANDERIA | G10: 1490 | H10: 0 | I10: =COMPRAS[[#This Row],[COSTO UNITARIO]]*COMPRAS[[#This Row],[CANTIDAD]] -> 0
A11: A005 | B11: 45945 | C11: =TEXT(COMPRAS[[#This Row],[FECHA]],"[$-es-CL]mmmm") -> octubre | D11: {=YEAR(IF(ISNUMBER(COMPRAS[[#This Row],[FECHA]]),COMPRAS[[#This Row],[FECHA]],FECHA.VALOR(COMPRAS[[#This Row],[FECHA]])))} -> 2025 | E11: =IFERROR(VLOOKUP(COMPRAS[[#This Row],[CODIGO]],INVENTARIO[],2,FALSE),"NO EXISTE") -> DETERGENTE CELESTE CON SUAVIZANTE DE 5 LITROS | F11: =IFERROR(VLOOKUP(COMPRAS[[#This Row],[CODIGO]],INVENTARIO[],3,FALSE),"NO EXISTE") -> LAVANDERIA | G11: 1490 | I11: =COMPRAS[[#This Row],[COSTO UNITARIO]]*COMPRAS[[#This Row],[CANTIDAD]] -> 0
A12: A006 | B12: 45945 | C12: =TEXT(COMPRAS[[#This Row],[FECHA]],"[$-es-CL]mmmm") -> octubre | D12: {=YEAR(IF(ISNUMBER(COMPRAS[[#This Row],[FECHA]]),COMPRAS[[#This Row],[FECHA]],FECHA.VALOR(COMPRAS[[#This Row],[FECHA]])))} -> 2025 | E12: =IFERROR(VLOOKUP(COMPRAS[[#This Row],[CODIGO]],INVENTARIO[],2,FALSE),"NO EXISTE") -> DETERGENTE NARANJO CON SUAVIZANTE DE 5 LITROS | F12: =IFERROR(VLOOKUP(COMPRAS[[#This Row],[CODIGO]],INVENTARIO[],3,FALSE),"NO EXISTE") -> LAVANDERIA | G12: 1490 | I12: =COMPRAS[[#This Row],[COSTO UNITARIO]]*COMPRAS[[#This Row],[CANTIDAD]] -> 0
A13: A007 | B13: 45945 | C13: =TEXT(COMPRAS[[#This Row],[FECHA]],"[$-es-CL]mmmm") -> octubre | D13: {=YEAR(IF(ISNUMBER(COMPRAS[[#This Row],[FECHA]]),COMPRAS[[#This Row],[FECHA]],FECHA.VALOR(COMPRAS[[#This Row],[FECHA]])))} -> 2025 | E13: =IFERROR(VLOOKUP(COMPRAS[[#This Row],[CODIGO]],INVENTARIO[],2,FALSE),"NO EXISTE") -> DETERGENTE ROSADO CON SUAVIZANTE DE 5 LITROS | F13: =IFERROR(VLOOKUP(COMPRAS[[#This Row],[CODIGO]],INVENTARIO[],3,FALSE),"NO EXISTE") -> LAVANDERIA | G13: 1490 | I13: =COMPRAS[[#This Row],[COSTO UNITARIO]]*COMPRAS[[#This Row],[CANTIDAD]] -> 0
A14: A008 | B14: 45945 | C14: =TEXT(COMPRAS[[#This Row],[FECHA]],"[$-es-CL]mmmm") -> octubre | D14: {=YEAR(IF(ISNUMBER(COMPRAS[[#This Row],[FECHA]]),COMPRAS[[#This Row],[FECHA]],FECHA.VALOR(COMPRAS[[#This Row],[FECHA]])))} -> 2025 | E14: =IFERROR(VLOOKUP(COMPRAS[[#This Row],[CODIGO]],INVENTARIO[],2,FALSE),"NO EXISTE") -> DETERGENTE PREMIUM AROMA OMO DE 3 LITROS (PACK DE 4 UNID) | F14: =IFERROR(VLOOKUP(COMPRAS[[#This Row],[CODIGO]],INVENTARIO[],3,FALSE),"NO EXISTE") -> LAVANDERIA | G14: 1350 | I14: =COMPRAS[[#This Row],[COSTO UNITARIO]]*COMPRAS[[#This Row],[CANTIDAD]] -> 0
A15: A009 | B15: 45945 | C15: =TEXT(COMPRAS[[#This Row],[FECHA]],"[$-es-CL]mmmm") -> octubre | D15: {=YEAR(IF(ISNUMBER(COMPRAS[[#This Row],[FECHA]]),COMPRAS[[#This Row],[FECHA]],FECHA.VALOR(COMPRAS[[#This Row],[FECHA]])))} -> 2025 | E15: =IFERROR(VLOOKUP(COMPRAS[[#This Row],[CODIGO]],INVENTARIO[],2,FALSE),"NO EXISTE") -> DETERGENTE DE BEBÉ 3 LITROS | F15: =IFERROR(VLOOKUP(COMPRAS[[#This Row],[CODIGO]],INVENTARIO[],3,FALSE),"NO EXISTE") -> LAVANDERIA | G15: 2450 | H15: 4 | I15: =COMPRAS[[#This Row],[COSTO UNITARIO]]*COMPRAS[[#This Row],[CANTIDAD]] -> 9800
A16: A010 | B16: 45945 | C16: =TEXT(COMPRAS[[#This Row],[FECHA]],"[$-es-CL]mmmm") -> octubre | D16: {=YEAR(IF(ISNUMBER(COMPRAS[[#This Row],[FECHA]]),COMPRAS[[#This Row],[FECHA]],FECHA.VALOR(COMPRAS[[#This Row],[FECHA]])))} -> 2025 | E16: =IFERROR(VLOOKUP(COMPRAS[[#This Row],[CODIGO]],INVENTARIO[],2,FALSE),"NO EXISTE") -> DETERGENTE OMO PARA DILUIR 3 LITROS | F16: =IFERROR(VLOOKUP(COMPRAS[[#This Row],[CODIGO]],INVENTARIO[],3,FALSE),"NO EXISTE") -> LAVANDERIA | G16: 981 | H16: 50 | I16: =COMPRAS[[#This Row],[COSTO UNITARIO]]*COMPRAS[[#This Row],[CANTIDAD]] -> 49050
A17: A011 | B17: 45945 | C17: =TEXT(COMPRAS[[#This Row],[FECHA]],"[$-es-CL]mmmm") -> octubre | D17: {=YEAR(IF(ISNUMBER(COMPRAS[[#This Row],[FECHA]]),COMPRAS[[#This Row],[FECHA]],FECHA.VALOR(COMPRAS[[#This Row],[FECHA]])))} -> 2025 | E17: =IFERROR(VLOOKUP(COMPRAS[[#This Row],[CODIGO]],INVENTARIO[],2,FALSE),"NO EXISTE") -> DETERGENTE OMO DE 400 ML | F17: =IFERROR(VLOOKUP(COMPRAS[[#This Row],[CODIGO]],INVENTARIO[],3,FALSE),"NO EXISTE") -> LAVANDERIA | G17: 733 | H17: 12 | I17: =COMPRAS[[#This Row],[COSTO UNITARIO]]*COMPRAS[[#This Row],[CANTIDAD]] -> 8796
A18: A012 | B18: 45945 | C18: =TEXT(COMPRAS[[#This Row],[FECHA]],"[$-es-CL]mmmm") -> octubre | D18: {=YEAR(IF(ISNUMBER(COMPRAS[[#This Row],[FECHA]]),COMPRAS[[#This Row],[FECHA]],FECHA.VALOR(COMPRAS[[#This Row],[FECHA]])))} -> 2025 | E18: =IFERROR(VLOOKUP(COMPRAS[[#This Row],[CODIGO]],INVENTARIO[],2,FALSE),"NO EXISTE") -> DETERGENTE OMO LIQUIDO BIDÓN 3 LITROS | F18: =IFERROR(VLOOKUP(COMPRAS[[#This Row],[CODIGO]],INVENTARIO[],3,FALSE),"NO EXISTE") -> LAVANDERIA | G18: 733 | H18: 24 | I18: =COMPRAS[[#This Row],[COSTO UNITARIO]]*COMPRAS[[#This Row],[CANTIDAD]] -> 17592
A19: A013 | B19: 45945 | C19: =TEXT(COMPRAS[[#This Row],[FECHA]],"[$-es-CL]mmmm") -> octubre | D19: {=YEAR(IF(ISNUMBER(COMPRAS[[#This Row],[FECHA]]),COMPRAS[[#This Row],[FECHA]],FECHA.VALOR(COMPRAS[[#This Row],[FECHA]])))} -> 2025 | E19: =IFERROR(VLOOKUP(COMPRAS[[#This Row],[CODIGO]],INVENTARIO[],2,FALSE),"NO EXISTE") -> DETERGENTE BIO KLINNING AZUL | F19: =IFERROR(VLOOKUP(COMPRAS[[#This Row],[CODIGO]],INVENTARIO[],3,FALSE),"NO EXISTE") -> LAVANDERIA | G19: 990 | H19: 15 | I19: =COMPRAS[[#This Row],[COSTO UNITARIO]]*COMPRAS[[#This Row],[CANTIDAD]] -> 14850
A20: A014 | B20: 45945 | C20: =TEXT(COMPRAS[[#This Row],[FECHA]],"[$-es-CL]mmmm") -> octubre | D20: {=YEAR(IF(ISNUMBER(COMPRAS[[#This Row],[FECHA]]),COMPRAS[[#This Row],[FECHA]],FECHA.VALOR(COMPRAS[[#This Row],[FECHA]])))} -> 2025 | E20: =IFERROR(VLOOKUP(COMPRAS[[#This Row],[CODIGO]],INVENTARIO[],2,FALSE),"NO EXISTE") -> DETERGENTE BIO KLINNING VERDE | F20: =IFERROR(VLOOKUP(COMPRAS[[#This Row],[CODIGO]],INVENTARIO[],3,FALSE),"NO EXISTE") -> LAVANDERIA | G20: 720 | H20: 10 | I20: =COMPRAS[[#This Row],[COSTO UNITARIO]]*COMPRAS[[#This Row],[CANTIDAD]] -> 7200
A21: A015 | B21: 45945 | C21: =TEXT(COMPRAS[[#This Row],[FECHA]],"[$-es-CL]mmmm") -> octubre | D21: {=YEAR(IF(ISNUMBER(COMPRAS[[#This Row],[FECHA]]),COMPRAS[[#This Row],[FECHA]],FECHA.VALOR(COMPRAS[[#This Row],[FECHA]])))} -> 2025 | E21: =IFERROR(VLOOKUP(COMPRAS[[#This Row],[CODIGO]],INVENTARIO[],2,FALSE),"NO EXISTE") -> DETERGENTE SOFT LIQUIDO BIDÓN DE 3 LITROS | F21: =IFERROR(VLOOKUP(COMPRAS[[#This Row],[CODIGO]],INVENTARIO[],3,FALSE),"NO EXISTE") -> LAVANDERIA | G21: 833 | H21: 9 | I21: =COMPRAS[[#This Row],[COSTO UNITARIO]]*COMPRAS[[#This Row],[CANTIDAD]] -> 7497
A22: A016 | B22: 45945 | C22: =TEXT(COMPRAS[[#This Row],[FECHA]],"[$-es-CL]mmmm") -> octubre | D22: {=YEAR(IF(ISNUMBER(COMPRAS[[#This Row],[FECHA]]),COMPRAS[[#This Row],[FECHA]],FECHA.VALOR(COMPRAS[[#This Row],[FECHA]])))} -> 2025 | E22: =IFERROR(VLOOKUP(COMPRAS[[#This Row],[CODIGO]],INVENTARIO[],2,FALSE),"NO EXISTE") -> DETERGENTE EN POLVO QUITA MANCHA ROSADO | F22: =IFERROR(VLOOKUP(COMPRAS[[#This Row],[CODIGO]],INVENTARIO[],3,FALSE),"NO EXISTE") -> LAVANDERIA | G22: 1010 | H22: 10 | I22: =COMPRAS[[#This Row],[COSTO UNITARIO]]*COMPRAS[[#This Row],[CANTIDAD]] -> 10100
A23: A017 | B23: 45945 | C23: =TEXT(COMPRAS[[#This Row],[FECHA]],"[$-es-CL]mmmm") -> octubre | D23: {=YEAR(IF(ISNUMBER(COMPRAS[[#This Row],[FECHA]]),COMPRAS[[#This Row],[FECHA]],FECHA.VALOR(COMPRAS[[#This Row],[FECHA]])))} -> 2025 | E23: =IFERROR(VLOOKUP(COMPRAS[[#This Row],[CODIGO]],INVENTARIO[],2,FALSE),"NO EXISTE") -> DETERGENTE EN POLVO QUITA MANCHA MORADO | F23: =IFERROR(VLOOKUP(COMPRAS[[#This Row],[CODIGO]],INVENTARIO[],3,FALSE),"NO EXISTE") -> LAVANDERIA | G23: 1333 | H23: 9 | I23: =COMPRAS[[#This Row],[COSTO UNITARIO]]*COMPRAS[[#This Row],[CANTIDAD]] -> 11997
A24: A018 | B24: 45945 | C24: =TEXT(COMPRAS[[#This Row],[FECHA]],"[$-es-CL]mmmm") -> octubre | D24: {=YEAR(IF(ISNUMBER(COMPRAS[[#This Row],[FECHA]]),COMPRAS[[#This Row],[FECHA]],FECHA.VALOR(COMPRAS[[#This Row],[FECHA]])))} -> 2025 | E24: =IFERROR(VLOOKUP(COMPRAS[[#This Row],[CODIGO]],INVENTARIO[],2,FALSE),"NO EXISTE") -> DETERGENTE EN POLVO VIRGINIA | F24: =IFERROR(VLOOKUP(COMPRAS[[#This Row],[CODIGO]],INVENTARIO[],3,FALSE),"NO EXISTE") -> LAVANDERIA | G24: 990 | H24: 9 | I24: =COMPRAS[[#This Row],[COSTO UNITARIO]]*COMPRAS[[#This Row],[CANTIDAD]] -> 8910
A25: A019 | B25: 45945 | C25: =TEXT(COMPRAS[[#This Row],[FECHA]],"[$-es-CL]mmmm") -> octubre | D25: {=YEAR(IF(ISNUMBER(COMPRAS[[#This Row],[FECHA]]),COMPRAS[[#This Row],[FECHA]],FECHA.VALOR(COMPRAS[[#This Row],[FECHA]])))} -> 2025 | E25: =IFERROR(VLOOKUP(COMPRAS[[#This Row],[CODIGO]],INVENTARIO[],2,FALSE),"NO EXISTE") -> CLORO ROPA BLANCA SPUM DE 1 LITRO | F25: =IFERROR(VLOOKUP(COMPRAS[[#This Row],[CODIGO]],INVENTARIO[],3,FALSE),"NO EXISTE") -> LAVANDERIA | G25: 1049 | H25: 10 | I25: =COMPRAS[[#This Row],[COSTO UNITARIO]]*COMPRAS[[#This Row],[CANTIDAD]] -> 10490
A26: A020 | B26: 45945 | C26: =TEXT(COMPRAS[[#This Row],[FECHA]],"[$-es-CL]mmmm") -> octubre | D26: {=YEAR(IF(ISNUMBER(COMPRAS[[#This Row],[FECHA]]),COMPRAS[[#This Row],[FECHA]],FECHA.VALOR(COMPRAS[[#This Row],[FECHA]])))} -> 2025 | E26: =IFERROR(VLOOKUP(COMPRAS[[#This Row],[CODIGO]],INVENTARIO[],2,FALSE),"NO EXISTE") -> CLORO ROPA A COLOR SPUM DE 1 LITRO | F26: =IFERROR(VLOOKUP(COMPRAS[[#This Row],[CODIGO]],INVENTARIO[],3,FALSE),"NO EXISTE") -> LAVANDERIA | I26: =COMPRAS[[#This Row],[COSTO UNITARIO]]*COMPRAS[[#This Row],[CANTIDAD]] -> 0
A27: A021 | B27: 45945 | C27: =TEXT(COMPRAS[[#This Row],[FECHA]],"[$-es-CL]mmmm") -> octubre | D27: {=YEAR(IF(ISNUMBER(COMPRAS[[#This Row],[FECHA]]),COMPRAS[[#This Row],[FECHA]],FECHA.VALOR(COMPRAS[[#This Row],[FECHA]])))} -> 2025 | E27: =IFERROR(VLOOKUP(COMPRAS[[#This Row],[CODIGO]],INVENTARIO[],2,FALSE),"NO EXISTE") -> VANISH BLANCO | F27: =IFERROR(VLOOKUP(COMPRAS[[#This Row],[CODIGO]],INVENTARIO[],3,FALSE),"NO EXISTE") -> LAVANDERIA | G27: 700 | H27: 12 | I27: =COMPRAS[[#This Row],[COSTO UNITARIO]]*COMPRAS[[#This Row],[CANTIDAD]] -> 8400
A28: A022 | B28: 45945 | C28: =TEXT(COMPRAS[[#This Row],[FECHA]],"[$-es-CL]mmmm") -> octubre | D28: {=YEAR(IF(ISNUMBER(COMPRAS[[#This Row],[FECHA]]),COMPRAS[[#This Row],[FECHA]],FECHA.VALOR(COMPRAS[[#This Row],[FECHA]])))} -> 2025 | E28: =IFERROR(VLOOKUP(COMPRAS[[#This Row],[CODIGO]],INVENTARIO[],2,FALSE),"NO EXISTE") -> VANISH ROSADO | F28: =IFERROR(VLOOKUP(COMPRAS[[#This Row],[CODIGO]],INVENTARIO[],3,FALSE),"NO EXISTE") -> LAVANDERIA | G28: 1110 | H28: 9 | I28: =COMPRAS[[#This Row],[COSTO UNITARIO]]*COMPRAS[[#This Row],[CANTIDAD]] -> 9990
A29: A023 | B29: 45945 | C29: =TEXT(COMPRAS[[#This Row],[FECHA]],"[$-es-CL]mmmm") -> octubre | D29: {=YEAR(IF(ISNUMBER(COMPRAS[[#This Row],[FECHA]]),COMPRAS[[#This Row],[FECHA]],FECHA.VALOR(COMPRAS[[#This Row],[FECHA]])))} -> 2025 | E29: =IFERROR(VLOOKUP(COMPRAS[[#This Row],[CODIGO]],INVENTARIO[],2,FALSE),"NO EXISTE") -> CLORO CONCENTRADO DE 5 LITROS | F29: =IFERROR(VLOOKUP(COMPRAS[[#This Row],[CODIGO]],INVENTARIO[],3,FALSE),"NO EXISTE") -> DESINFECCIÓN | G29: 1000 | H29: 10 | I29: =COMPRAS[[#This Row],[COSTO UNITARIO]]*COMPRAS[[#This Row],[CANTIDAD]] -> 10000
A30: A024 | B30: 45945 | C30: =TEXT(COMPRAS[[#This Row],[FECHA]],"[$-es-CL]mmmm") -> octubre | D30: {=YEAR(IF(ISNUMBER(COMPRAS[[#This Row],[FECHA]]),COMPRAS[[#This Row],[FECHA]],FECHA.VALOR(COMPRAS[[#This Row],[FECHA]])))} -> 2025 | E30: =IFERROR(VLOOKUP(COMPRAS[[#This Row],[CODIGO]],INVENTARIO[],2,FALSE),"NO EXISTE") -> CLORINDA DE 1 LITRO | F30: =IFERROR(VLOOKUP(COMPRAS[[#This Row],[CODIGO]],INVENTARIO[],3,FALSE),"NO EXISTE") -> DESINFECCIÓN | G30: 667 | H30: 12 | I30: =COMPRAS[[#This Row],[COSTO UNITARIO]]*COMPRAS[[#This Row],[CANTIDAD]] -> 8004
A31: A025 | B31: 45945 | C31: =TEXT(COMPRAS[[#This Row],[FECHA]],"[$-es-CL]mmmm") -> octubre | D31: {=YEAR(IF(ISNUMBER(COMPRAS[[#This Row],[FECHA]]),COMPRAS[[#This Row],[FECHA]],FECHA.VALOR(COMPRAS[[#This Row],[FECHA]])))} -> 2025 | E31: =IFERROR(VLOOKUP(COMPRAS[[#This Row],[CODIGO]],INVENTARIO[],2,FALSE),"NO EXISTE") -> CLORO GEL CLOROX | F31: =IFERROR(VLOOKUP(COMPRAS[[#This Row],[CODIGO]],INVENTARIO[],3,FALSE),"NO EXISTE") -> DESINFECCIÓN | G31: 666 | H31: 9 | I31: =COMPRAS[[#This Row],[COSTO UNITARIO]]*COMPRAS[[#This Row],[CANTIDAD]] -> 5994
A32: A026 | B32: 45945 | C32: =TEXT(COMPRAS[[#This Row],[FECHA]],"[$-es-CL]mmmm") -> octubre | D32: {=YEAR(IF(ISNUMBER(COMPRAS[[#This Row],[FECHA]]),COMPRAS[[#This Row],[FECHA]],FECHA.VALOR(COMPRAS[[#This Row],[FECHA]])))} -> 2025 | E32: =IFERROR(VLOOKUP(COMPRAS[[#This Row],[CODIGO]],INVENTARIO[],2,FALSE),"NO EXISTE") -> CLORO IGENIX LIQUIDO | F32: =IFERROR(VLOOKUP(COMPRAS[[#This Row],[CODIGO]],INVENTARIO[],3,FALSE),"NO EXISTE") -> DESINFECCIÓN | G32: 599 | H32: 12 | I32: =COMPRAS[[#This Row],[COSTO UNITARIO]]*COMPRAS[[#This Row],[CANTIDAD]] -> 7188
A33: A027 | B33: 45945 | C33: =TEXT(COMPRAS[[#This Row],[FECHA]],"[$-es-CL]mmmm") -> octubre | D33: {=YEAR(IF(ISNUMBER(COMPRAS[[#This Row],[FECHA]]),COMPRAS[[#This Row],[FECHA]],FECHA.VALOR(COMPRAS[[#This Row],[FECHA]])))} -> 2025 | E33: =IFERROR(VLOOKUP(COMPRAS[[#This Row],[CODIGO]],INVENTARIO[],2,FALSE),"NO EXISTE") -> CLORINDA CLORO GEL | F33: =IFERROR(VLOOKUP(COMPRAS[[#This Row],[CODIGO]],INVENTARIO[],3,FALSE),"NO EXISTE") -> DESINFECCIÓN | G33: 599 | H33: 12 | I33: =COMPRAS[[#This Row],[COSTO UNITARIO]]*COMPRAS[[#This Row],[CANTIDAD]] -> 7188
A34: A028 | B34: 45945 | C34: =TEXT(COMPRAS[[#This Row],[FECHA]],"[$-es-CL]mmmm") -> octubre | D34: {=YEAR(IF(ISNUMBER(COMPRAS[[#This Row],[FECHA]]),COMPRAS[[#This Row],[FECHA]],FECHA.VALOR(COMPRAS[[#This Row],[FECHA]])))} -> 2025 | E34: =IFERROR(VLOOKUP(COMPRAS[[#This Row],[CODIGO]],INVENTARIO[],2,FALSE),"NO EXISTE") -> CLORINDA CLORO GEL EXCEL MORADO | F34: =IFERROR(VLOOKUP(COMPRAS[[#This Row],[CODIGO]],INVENTARIO[],3,FALSE),"NO EXISTE") -> DESINFECCIÓN | G34: 833 | H34: 12 | I34: =COMPRAS[[#This Row],[COSTO UNITARIO]]*COMPRAS[[#This Row],[CANTIDAD]] -> 9996
A35: A029 | B35: 45945 | C35: =TEXT(COMPRAS[[#This Row],[FECHA]],"[$-es-CL]mmmm") -> octubre | D35: {=YEAR(IF(ISNUMBER(COMPRAS[[#This Row],[FECHA]]),COMPRAS[[#This Row],[FECHA]],FECHA.VALOR(COMPRAS[[#This Row],[FECHA]])))} -> 2025 | E35: =IFERROR(VLOOKUP(COMPRAS[[#This Row],[CODIGO]],INVENTARIO[],2,FALSE),"NO EXISTE") -> CLORINDA CLORO GEL EXCEL AMARILLO | F35: =IFERROR(VLOOKUP(COMPRAS[[#This Row],[CODIGO]],INVENTARIO[],3,FALSE),"NO EXISTE") -> DESINFECCIÓN | G35: 1443 | H35: 9 | I35: =COMPRAS[[#This Row],[COSTO UNITARIO]]*COMPRAS[[#This Row],[CANTIDAD]] -> 12987
A36: A030 | B36: 45945 | C36: =TEXT(COMPRAS[[#This Row],[FECHA]],"[$-es-CL]mmmm") -> octubre | D36: {=YEAR(IF(ISNUMBER(COMPRAS[[#This Row],[FECHA]]),COMPRAS[[#This Row],[FECHA]],FECHA.VALOR(COMPRAS[[#This Row],[FECHA]])))} -> 2025 | E36: =IFERROR(VLOOKUP(COMPRAS[[#This Row],[CODIGO]],INVENTARIO[],2,FALSE),"NO EXISTE") -> ANTIGRASA SPUM DE 2 LITROS | F36: =IFERROR(VLOOKUP(COMPRAS[[#This Row],[CODIGO]],INVENTARIO[],3,FALSE),"NO EXISTE") -> COCINA | G36: 698 | H36: 5 | I36: =COMPRAS[[#This Row],[COSTO UNITARIO]]*COMPRAS[[#This Row],[CANTIDAD]] -> 3490
A37: A031 | B37: 45945 | C37: =TEXT(COMPRAS[[#This Row],[FECHA]],"[$-es-CL]mmmm") -> octubre | D37: {=YEAR(IF(ISNUMBER(COMPRAS[[#This Row],[FECHA]]),COMPRAS[[#This Row],[FECHA]],FECHA.VALOR(COMPRAS[[#This Row],[FECHA]])))} -> 2025 | E37: =IFERROR(VLOOKUP(COMPRAS[[#This Row],[CODIGO]],INVENTARIO[],2,FALSE),"NO EXISTE") -> ANTIGRASA SPUM DE 500 ML | F37: =IFERROR(VLOOKUP(COMPRAS[[#This Row],[CODIGO]],INVENTARIO[],3,FALSE),"NO EXISTE") -> COCINA | G37: 700 | H37: 12 | I37: =COMPRAS[[#This Row],[COSTO UNITARIO]]*COMPRAS[[#This Row],[CANTIDAD]] -> 8400
A38: A032 | B38: 45945 | C38: =TEXT(COMPRAS[[#This Row],[FECHA]],"[$-es-CL]mmmm") -> octubre | D38: {=YEAR(IF(ISNUMBER(COMPRAS[[#This Row],[FECHA]]),COMPRAS[[#This Row],[FECHA]],FECHA.VALOR(COMPRAS[[#This Row],[FECHA]])))} -> 2025 | E38: =IFERROR(VLOOKUP(COMPRAS[[#This Row],[CODIGO]],INVENTARIO[],2,FALSE),"NO EXISTE") -> SACASARRO SPUM DE 2 LITROS | F38: =IFERROR(VLOOKUP(COMPRAS[[#This Row],[CODIGO]],INVENTARIO[],3,FALSE),"NO EXISTE") -> COCINA | G38: 1790 | H38: 6 | I38: =COMPRAS[[#This Row],[COSTO UNITARIO]]*COMPRAS[[#This Row],[CANTIDAD]] -> 10740
... A44: A038 | B44: 45945 | C44: =TEXT(COMPRAS[[#This Row],[FECHA]],"[$-es-CL]mmmm") -> octubre | D44: {=YEAR(IF(ISNUMBER(COMPRAS[[#This Row],[FECHA]]),COMPRAS[[#This Row],[FECHA]],FECHA.VALOR(COMPRAS[[#This Row],[FECHA]])))} -> 2025 | E44: =IFERROR(VLOOKUP(COMPRAS[[#This Row],[CODIGO]],INVENTARIO[],2,FALSE),"NO EXISTE") -> CIF | F44: =IFERROR(VLOOKUP(COMPRAS[[#This Row],[CODIGO]],INVENTARIO[],3,FALSE),"NO EXISTE") -> COCINA | G44: 990 | H44: 12 | I44: =COMPRAS[[#This Row],[COSTO UNITARIO]]*COMPRAS[[#This Row],[CANTIDAD]] -> 11880
A45: A039 | B45: 45945 | C45: =TEXT(COMPRAS[[#This Row],[FECHA]],"[$-es-CL]mmmm") -> octubre | D45: {=YEAR(IF(ISNUMBER(COMPRAS[[#This Row],[FECHA]]),COMPRAS[[#This Row],[FECHA]],FECHA.VALOR(COMPRAS[[#This Row],[FECHA]])))} -> 2025 | E45: =IFERROR(VLOOKUP(COMPRAS[[#This Row],[CODIGO]],INVENTARIO[],2,FALSE),"NO EXISTE") -> LUSTRA MUEBLES | F45: =IFERROR(VLOOKUP(COMPRAS[[#This Row],[CODIGO]],INVENTARIO[],3,FALSE),"NO EXISTE") -> COCINA | H45: 50 | I45: =COMPRAS[[#This Row],[COSTO UNITARIO]]*COMPRAS[[#This Row],[CANTIDAD]] -> 0
A46: A040 | B46: 45945 | C46: =TEXT(COMPRAS[[#This Row],[FECHA]],"[$-es-CL]mmmm") -> octubre | D46: {=YEAR(IF(ISNUMBER(COMPRAS[[#This Row],[FECHA]]),COMPRAS[[#This Row],[FECHA]],FECHA.VALOR(COMPRAS[[#This Row],[FECHA]])))} -> 2025 | E46: =IFERROR(VLOOKUP(COMPRAS[[#This Row],[CODIGO]],INVENTARIO[],2,FALSE),"NO EXISTE") -> LIMPIA VIDRIOS DE 500CC | F46: =IFERROR(VLOOKUP(COMPRAS[[#This Row],[CODIGO]],INVENTARIO[],3,FALSE),"NO EXISTE") -> COCINA | G46: 500 | H46: 50 | I46: =COMPRAS[[#This Row],[COSTO UNITARIO]]*COMPRAS[[#This Row],[CANTIDAD]] -> 25000
A47: A041 | B47: 45945 | C47: =TEXT(COMPRAS[[#This Row],[FECHA]],"[$-es-CL]mmmm") -> octubre | D47: {=YEAR(IF(ISNUMBER(COMPRAS[[#This Row],[FECHA]]),COMPRAS[[#This Row],[FECHA]],FECHA.VALOR(COMPRAS[[#This Row],[FECHA]])))} -> 2025 | E47: =IFERROR(VLOOKUP(COMPRAS[[#This Row],[CODIGO]],INVENTARIO[],2,FALSE),"NO EXISTE") -> LIMPIA PISOS FLOTANTE | F47: =IFERROR(VLOOKUP(COMPRAS[[#This Row],[CODIGO]],INVENTARIO[],3,FALSE),"NO EXISTE") -> COCINA | G47: 85 | H47: 400 | I47: =COMPRAS[[#This Row],[COSTO UNITARIO]]*COMPRAS[[#This Row],[CANTIDAD]] -> 34000
A48: A042 | B48: 45945 | C48: =TEXT(COMPRAS[[#This Row],[FECHA]],"[$-es-CL]mmmm") -> octubre | D48: {=YEAR(IF(ISNUMBER(COMPRAS[[#This Row],[FECHA]]),COMPRAS[[#This Row],[FECHA]],FECHA.VALOR(COMPRAS[[#This Row],[FECHA]])))} -> 2025 | E48: =IFERROR(VLOOKUP(COMPRAS[[#This Row],[CODIGO]],INVENTARIO[],2,FALSE),"NO EXISTE") -> VIRUTILLA | F48: =IFERROR(VLOOKUP(COMPRAS[[#This Row],[CODIGO]],INVENTARIO[],3,FALSE),"NO EXISTE") -> COCINA | G48: 56 | H48: 100 | I48: =COMPRAS[[#This Row],[COSTO UNITARIO]]*COMPRAS[[#This Row],[CANTIDAD]] -> 5600
A49: A043 | B49: 45945 | C49: =TEXT(COMPRAS[[#This Row],[FECHA]],"[$-es-CL]mmmm") -> octubre | D49: {=YEAR(IF(ISNUMBER(COMPRAS[[#This Row],[FECHA]]),COMPRAS[[#This Row],[FECHA]],FECHA.VALOR(COMPRAS[[#This Row],[FECHA]])))} -> 2025 | E49: =IFERROR(VLOOKUP(COMPRAS[[#This Row],[CODIGO]],INVENTARIO[],2,FALSE),"NO EXISTE") -> LIMPIA PISOS SPUM COLOR ROJO | F49: =IFERROR(VLOOKUP(COMPRAS[[#This Row],[CODIGO]],INVENTARIO[],3,FALSE),"NO EXISTE") -> SUPERFICIE | G49: 591 | H49: 24 | I49: =COMPRAS[[#This Row],[COSTO UNITARIO]]*COMPRAS[[#This Row],[CANTIDAD]] -> 14184
A50: A044 | B50: 45945 | C50: =TEXT(COMPRAS[[#This Row],[FECHA]],"[$-es-CL]mmmm") -> octubre | D50: {=YEAR(IF(ISNUMBER(COMPRAS[[#This Row],[FECHA]]),COMPRAS[[#This Row],[FECHA]],FECHA.VALOR(COMPRAS[[#This Row],[FECHA]])))} -> 2025 | E50: =IFERROR(VLOOKUP(COMPRAS[[#This Row],[CODIGO]],INVENTARIO[],2,FALSE),"NO EXISTE") -> LIMPIA PISOS SPUM COLOR AZUL | F50: =IFERROR(VLOOKUP(COMPRAS[[#This Row],[CODIGO]],INVENTARIO[],3,FALSE),"NO EXISTE") -> SUPERFICIE | G50: 1100 | H50: 12 | I50: =COMPRAS[[#This Row],[COSTO UNITARIO]]*COMPRAS[[#This Row],[CANTIDAD]] -> 13200
A51: A045 | B51: 45945 | C51: =TEXT(COMPRAS[[#This Row],[FECHA]],"[$-es-CL]mmmm") -> octubre | D51: {=YEAR(IF(ISNUMBER(COMPRAS[[#This Row],[FECHA]]),COMPRAS[[#This Row],[FECHA]],FECHA.VALOR(COMPRAS[[#This Row],[FECHA]])))} -> 2025 | E51: =IFERROR(VLOOKUP(COMPRAS[[#This Row],[CODIGO]],INVENTARIO[],2,FALSE),"NO EXISTE") -> LIMPIA PISOS BRILLEX AMARILLO | F51: =IFERROR(VLOOKUP(COMPRAS[[#This Row],[CODIGO]],INVENTARIO[],3,FALSE),"NO EXISTE") -> SUPERFICIE | G51: 158 | H51: 12 | I51: =COMPRAS[[#This Row],[COSTO UNITARIO]]*COMPRAS[[#This Row],[CANTIDAD]] -> 1896
A52: A046 | B52: 45945 | C52: =TEXT(COMPRAS[[#This Row],[FECHA]],"[$-es-CL]mmmm") -> octubre | D52: {=YEAR(IF(ISNUMBER(COMPRAS[[#This Row],[FECHA]]),COMPRAS[[#This Row],[FECHA]],FECHA.VALOR(COMPRAS[[#This Row],[FECHA]])))} -> 2025 | E52: =IFERROR(VLOOKUP(COMPRAS[[#This Row],[CODIGO]],INVENTARIO[],2,FALSE),"NO EXISTE") -> LIMPIA PISOS AROMAX AZUL | F52: =IFERROR(VLOOKUP(COMPRAS[[#This Row],[CODIGO]],INVENTARIO[],3,FALSE),"NO EXISTE") -> SUPERFICIE | G52: 650 | H52: 12 | I52: =COMPRAS[[#This Row],[COSTO UNITARIO]]*COMPRAS[[#This Row],[CANTIDAD]] -> 7800
A53: A047 | B53: 45945 | C53: =TEXT(COMPRAS[[#This Row],[FECHA]],"[$-es-CL]mmmm") -> octubre | D53: {=YEAR(IF(ISNUMBER(COMPRAS[[#This Row],[FECHA]]),COMPRAS[[#This Row],[FECHA]],FECHA.VALOR(COMPRAS[[#This Row],[FECHA]])))} -> 2025 | E53: =IFERROR(VLOOKUP(COMPRAS[[#This Row],[CODIGO]],INVENTARIO[],2,FALSE),"NO EXISTE") -> LIMPIA PISOS AROMAX ROSADO | F53: =IFERROR(VLOOKUP(COMPRAS[[#This Row],[CODIGO]],INVENTARIO[],3,FALSE),"NO EXISTE") -> SUPERFICIE | G53: 750 | H53: 10 | I53: =COMPRAS[[#This Row],[COSTO UNITARIO]]*COMPRAS[[#This Row],[CANTIDAD]] -> 7500
A54: A048 | B54: 45945 | C54: =TEXT(COMPRAS[[#This Row],[FECHA]],"[$-es-CL]mmmm") -> octubre | D54: {=YEAR(IF(ISNUMBER(COMPRAS[[#This Row],[FECHA]]),COMPRAS[[#This Row],[FECHA]],FECHA.VALOR(COMPRAS[[#This Row],[FECHA]])))} -> 2025 | E54: =IFERROR(VLOOKUP(COMPRAS[[#This Row],[CODIGO]],INVENTARIO[],2,FALSE),"NO EXISTE") -> LIMPIA PISOS AROMAX MORADO | F54: =IFERROR(VLOOKUP(COMPRAS[[#This Row],[CODIGO]],INVENTARIO[],3,FALSE),"NO EXISTE") -> SUPERFICIE | G54: 250 | H54: 12 | I54: =COMPRAS[[#This Row],[COSTO UNITARIO]]*COMPRAS[[#This Row],[CANTIDAD]] -> 3000
A55: A049 | B55: 45945 | C55: =TEXT(COMPRAS[[#This Row],[FECHA]],"[$-es-CL]mmmm") -> octubre | D55: {=YEAR(IF(ISNUMBER(COMPRAS[[#This Row],[FECHA]]),COMPRAS[[#This Row],[FECHA]],FECHA.VALOR(COMPRAS[[#This Row],[FECHA]])))} -> 2025 | E55: =IFERROR(VLOOKUP(COMPRAS[[#This Row],[CODIGO]],INVENTARIO[],2,FALSE),"NO EXISTE") -> LIMPIA PISOS POETT ROSADO | F55: =IFERROR(VLOOKUP(COMPRAS[[#This Row],[CODIGO]],INVENTARIO[],3,FALSE),"NO EXISTE") -> SUPERFICIE | G55: 790 | H55: 6 | I55: =COMPRAS[[#This Row],[COSTO UNITARIO]]*COMPRAS[[#This Row],[CANTIDAD]] -> 4740
A56: A050 | B56: 45946 | C56: =TEXT(COMPRAS[[#This Row],[FECHA]],"[$-es-CL]mmmm") -> octubre | D56: {=YEAR(IF(ISNUMBER(COMPRAS[[#This Row],[FECHA]]),COMPRAS[[#This Row],[FECHA]],FECHA.VALOR(COMPRAS[[#This Row],[FECHA]])))} -> 2025 | E56: =IFERROR(VLOOKUP(COMPRAS[[#This Row],[CODIGO]],INVENTARIO[],2,FALSE),"NO EXISTE") -> LIMPIA PISOS POETT MORADO OSCURO | F56: =IFERROR(VLOOKUP(COMPRAS[[#This Row],[CODIGO]],INVENTARIO[],3,FALSE),"NO EXISTE") -> SUPERFICIE | G56: 350 | H56: 24 | I56: =COMPRAS[[#This Row],[COSTO UNITARIO]]*COMPRAS[[#This Row],[CANTIDAD]] -> 8400
A57: A051 | B57: 45946 | C57: =TEXT(COMPRAS[[#This Row],[FECHA]],"[$-es-CL]mmmm") -> octubre | D57: {=YEAR(IF(ISNUMBER(COMPRAS[[#This Row],[FECHA]]),COMPRAS[[#This Row],[FECHA]],FECHA.VALOR(COMPRAS[[#This Row],[FECHA]])))} -> 2025 | E57: =IFERROR(VLOOKUP(COMPRAS[[#This Row],[CODIGO]],INVENTARIO[],2,FALSE),"NO EXISTE") -> ESCOBILLON | F57: =IFERROR(VLOOKUP(COMPRAS[[#This Row],[CODIGO]],INVENTARIO[],3,FALSE),"NO EXISTE") -> SUPERFICIE | G57: 99 | H57: 40 | I57: =COMPRAS[[#This Row],[COSTO UNITARIO]]*COMPRAS[[#This Row],[CANTIDAD]] -> 3960
A58: A052 | B58: 45946 | C58: =TEXT(COMPRAS[[#This Row],[FECHA]],"[$-es-CL]mmmm") -> octubre | D58: {=YEAR(IF(ISNUMBER(COMPRAS[[#This Row],[FECHA]]),COMPRAS[[#This Row],[FECHA]],FECHA.VALOR(COMPRAS[[#This Row],[FECHA]])))} -> 2025 | E58: =IFERROR(VLOOKUP(COMPRAS[[#This Row],[CODIGO]],INVENTARIO[],2,FALSE),"NO EXISTE") -> LIMPIA PISOS POETT MORADO CLARO | F58: =IFERROR(VLOOKUP(COMPRAS[[#This Row],[CODIGO]],INVENTARIO[],3,FALSE),"NO EXISTE") -> SUPERFICIE | I58: =COMPRAS[[#This Row],[COSTO UNITARIO]]*COMPRAS[[#This Row],[CANTIDAD]] -> 0
A59: A053 | B59: 45946 | C59: =TEXT(COMPRAS[[#This Row],[FECHA]],"[$-es-CL]mmmm") -> octubre | D59: {=YEAR(IF(ISNUMBER(COMPRAS[[#This Row],[FECHA]]),COMPRAS[[#This Row],[FECHA]],FECHA.VALOR(COMPRAS[[#This Row],[FECHA]])))} -> 2025 | E59: =IFERROR(VLOOKUP(COMPRAS[[#This Row],[CODIGO]],INVENTARIO[],2,FALSE),"NO EXISTE") -> LIMPIA PISOS POETT AZUL | F59: =IFERROR(VLOOKUP(COMPRAS[[#This Row],[CODIGO]],INVENTARIO[],3,FALSE),"NO EXISTE") -> SUPERFICIE | I59: =COMPRAS[[#This Row],[COSTO UNITARIO]]*COMPRAS[[#This Row],[CANTIDAD]] -> 0
A60: A054 | B60: 45946 | C60: =TEXT(COMPRAS[[#This Row],[FECHA]],"[$-es-CL]mmmm") -> octubre | D60: {=YEAR(IF(ISNUMBER(COMPRAS[[#This Row],[FECHA]]),COMPRAS[[#This Row],[FECHA]],FECHA.VALOR(COMPRAS[[#This Row],[FECHA]])))} -> 2025 | E60: =IFERROR(VLOOKUP(COMPRAS[[#This Row],[CODIGO]],INVENTARIO[],2,FALSE),"NO EXISTE") -> CERA DE 1 LITRO | F60: =IFERROR(VLOOKUP(COMPRAS[[#This Row],[CODIGO]],INVENTARIO[],3,FALSE),"NO EXISTE") -> SUPERFICIE | I60: =COMPRAS[[#This Row],[COSTO UNITARIO]]*COMPRAS[[#This Row],[CANTIDAD]] -> 0
A61: A055 | B61: 45946 | C61: =TEXT(COMPRAS[[#This Row],[FECHA]],"[$-es-CL]mmmm") -> octubre | D61: {=YEAR(IF(ISNUMBER(COMPRAS[[#This Row],[FECHA]]),COMPRAS[[#This Row],[FECHA]],FECHA.VALOR(COMPRAS[[#This Row],[FECHA]])))} -> 2025 | E61: =IFERROR(VLOOKUP(COMPRAS[[#This Row],[CODIGO]],INVENTARIO[],2,FALSE),"NO EXISTE") -> CERA DE 2 LITROS | F61: =IFERROR(VLOOKUP(COMPRAS[[#This Row],[CODIGO]],INVENTARIO[],3,FALSE),"NO EXISTE") -> SUPERFICIE | I61: =COMPRAS[[#This Row],[COSTO UNITARIO]]*COMPRAS[[#This Row],[CANTIDAD]] -> 0
A62: A056 | B62: 45955 | C62: =TEXT(COMPRAS[[#This Row],[FECHA]],"[$-es-CL]mmmm") -> octubre | D62: {=YEAR(IF(ISNUMBER(COMPRAS[[#This Row],[FECHA]]),COMPRAS[[#This Row],[FECHA]],FECHA.VALOR(COMPRAS[[#This Row],[FECHA]])))} -> 2025 | E62: =IFERROR(VLOOKUP(COMPRAS[[#This Row],[CODIGO]],INVENTARIO[],2,FALSE),"NO EXISTE") -> PASTILLAS DE CLORO CHICAS PARA BAÑO | F62: =IFERROR(VLOOKUP(COMPRAS[[#This Row],[CODIGO]],INVENTARIO[],3,FALSE),"NO EXISTE") -> SUPERFICIE | G62: 9000 | H62: 24 | I62: =COMPRAS[[#This Row],[COSTO UNITARIO]]*COMPRAS[[#This Row],[CANTIDAD]] -> 216000
A63: A057 | B63: 45955 | C63: =TEXT(COMPRAS[[#This Row],[FECHA]],"[$-es-CL]mmmm") -> octubre | D63: {=YEAR(IF(ISNUMBER(COMPRAS[[#This Row],[FECHA]]),COMPRAS[[#This Row],[FECHA]],FECHA.VALOR(COMPRAS[[#This Row],[FECHA]])))} -> 2025 | E63: =IFERROR(VLOOKUP(COMPRAS[[#This Row],[CODIGO]],INVENTARIO[],2,FALSE),"NO EXISTE") -> TOALLITAS DESINFECTANTE IGENIX | F63: =IFERROR(VLOOKUP(COMPRAS[[#This Row],[CODIGO]],INVENTARIO[],3,FALSE),"NO EXISTE") -> SUPERFICIE | G63: 3330 | H63: 24 | I63: =COMPRAS[[#This Row],[COSTO UNITARIO]]*COMPRAS[[#This Row],[CANTIDAD]] -> 79920
A64: A058

Sheet VENTAS
A1: VENTAS
J4: TOTAL VENTA | K4: TOTAL UTILIDAD
J5: =SUBTOTAL(9,J6:J212) -> 0 | K5: =SUBTOTAL(9,K6:K212) -> 0
A6: CODIGO | B6: FECHA | C6: MES | D6: AÑO | E6: NOMBRE DEL PRODUCTO | F6: CATEGORIA | G6: PRECIO DE VENTA | H6: COSTO UNITARIO | I6: CANTIDAD | J6: TOTAL DE LA VENTA | K6: UTILIDAD
A7: A001 | B7: 45047 | C7: =TEXT(VENTAS[[#This Row],[FECHA]],"[$-es-CL]mmmm") -> mayo | D7: {=YEAR(IF(ISNUMBER(VENTAS[[#This Row],[FECHA]]),VENTAS[[#This Row],[FECHA]],FECHA.VALOR(VENTAS[[#This Row],[FECHA]])))} -> 2023 | E7: =IFERROR(VLOOKUP(VENTAS[[#This Row],[CODIGO]],INVENTARIO[],2,FALSE),"NO EXISTE") -> DETERGENTE BIO AZUL DE 5 LITROS | F7: =IFERROR(VLOOKUP(VENTAS[[#This Row],[CODIGO]],INVENTARIO[],3,FALSE),"NO EXISTE") -> LAVANDERIA | G7: =IFERROR(VLOOKUP(VENTAS[[#This Row],[CODIGO]],INVENTARIO[],8,FALSE),"NO EXISTE") -> 1800 | H7: =IFERROR(VLOOKUP(VENTAS[[#This Row],[CODIGO]],INVENTARIO[],7,FALSE),"NO EXISTE") -> 920 | I7: 0 | J7: =VENTAS[[#This Row],[PRECIO DE VENTA]]*VENTAS[[#This Row],[CANTIDAD]] -> 0 | K7: =VENTAS[[#This Row],[TOTAL DE LA VENTA]]-VENTAS[[#This Row],[COSTO UNITARIO]]*VENTAS[[#This Row],[CANTIDAD]] -> 0
A8: A002 | C8: =TEXT(VENTAS[[#This Row],[FECHA]],"[$-es-CL]mmmm") -> enero | D8: {=YEAR(IF(ISNUMBER(VENTAS[[#This Row],[FECHA]]),VENTAS[[#This Row],[FECHA]],FECHA.VALOR(VENTAS[[#This Row],[FECHA]])))} -> #NAME? | E8: =IFERROR(VLOOKUP(VENTAS[[#This Row],[CODIGO]],INVENTARIO[],2,FALSE),"NO EXISTE") -> DETERGENTE BIO VERDE DE 5 LITROS | F8: =IFERROR(VLOOKUP(VENTAS[[#This Row],[CODIGO]],INVENTARIO[],3,FALSE),"NO EXISTE") -> LAVANDERIA | G8: =IFERROR(VLOOKUP(VENTAS[[#This Row],[CODIGO]],INVENTARIO[],8,FALSE),"NO EXISTE") -> 1800 | H8: =IFERROR(VLOOKUP(VENTAS[[#This Row],[CODIGO]],INVENTARIO[],7,FALSE),"NO EXISTE") -> 920 | I8: 0 | J8: =VENTAS[[#This Row],[PRECIO DE VENTA]]*VENTAS[[#This Row],[CANTIDAD]] -> 0 | K8: =VENTAS[[#This Row],[TOTAL DE LA VENTA]]-VENTAS[[#This Row],[COSTO UNITARIO]]*VENTAS[[#This Row],[CANTIDAD]] -> 0
A9: A003 | C9: =TEXT(VENTAS[[#This Row],[FECHA]],"[$-es-CL]mmmm") -> enero | D9: {=YEAR(IF(ISNUMBER(VENTAS[[#This Row],[FECHA]]),VENTAS[[#This Row],[FECHA]],FECHA.VALOR(VENTAS[[#This Row],[FECHA]])))} -> #NAME? | E9: =IFERROR(VLOOKUP(VENTAS[[#This Row],[CODIGO]],INVENTARIO[],2,FALSE),"NO EXISTE") -> DETERGENTE MORADO CON SUAVIZANTE DE 5 LITROS | F9: =IFERROR(VLOOKUP(VENTAS[[#This Row],[CODIGO]],INVENTARIO[],3,FALSE),"NO EXISTE") -> LAVANDERIA | G9: =IFERROR(VLOOKUP(VENTAS[[#This Row],[CODIGO]],INVENTARIO[],8,FALSE),"NO EXISTE") -> 2500 | H9: =IFERROR(VLOOKUP(VENTAS[[#This Row],[CODIGO]],INVENTARIO[],7,FALSE),"NO EXISTE") -> 1490 | I9: 0 | J9: =VENTAS[[#This Row],[PRECIO DE VENTA]]*VENTAS[[#This Row],[CANTIDAD]] -> 0 | K9: =VENTAS[[#This Row],[TOTAL DE LA VENTA]]-VENTAS[[#This Row],[COSTO UNITARIO]]*VENTAS[[#This Row],[CANTIDAD]] -> 0
A10: A004 | C10: =TEXT(VENTAS[[#This Row],[FECHA]],"[$-es-CL]mmmm") -> enero | D10: {=YEAR(IF(ISNUMBER(VENTAS[[#This Row],[FECHA]]),VENTAS[[#This Row],[FECHA]],FECHA.VALOR(VENTAS[[#This Row],[FECHA]])))} -> #NAME? | E10: =IFERROR(VLOOKUP(VENTAS[[#This Row],[CODIGO]],INVENTARIO[],2,FALSE),"NO EXISTE") -> DETERGENTE BLANCO CON SUAVIZANTE DE 5 LITROS | F10: =IFERROR(VLOOKUP(VENTAS[[#This Row],[CODIGO]],INVENTARIO[],3,FALSE),"NO EXISTE") -> LAVANDERIA | G10: =IFERROR(VLOOKUP(VENTAS[[#This Row],[CODIGO]],INVENTARIO[],8,FALSE),"NO EXISTE") -> 2500 | H10: =IFERROR(VLOOKUP(VENTAS[[#This Row],[CODIGO]],INVENTARIO[],7,FALSE),"NO EXISTE") -> 1490 | I10: 0 | J10: =VENTAS[[#This Row],[PRECIO DE VENTA]]*VENTAS[[#This Row],[CANTIDAD]] -> 0 | K10: =VENTAS[[#This Row],[TOTAL DE LA VENTA]]-VENTAS[[#This Row],[COSTO UNITARIO]]*VENTAS[[#This Row],[CANTIDAD]] -> 0
A11: A005 | C11: =TEXT(VENTAS[[#This Row],[FECHA]],"[$-es-CL]mmmm") -> enero | D11: {=YEAR(IF(ISNUMBER(VENTAS[[#This Row],[FECHA]]),VENTAS[[#This Row],[FECHA]],FECHA.VALOR(VENTAS[[#This Row],[FECHA]])))} -> #NAME? | E11: =IFERROR(VLOOKUP(VENTAS[[#This Row],[CODIGO]],INVENTARIO[],2,FALSE),"NO EXISTE") -> DETERGENTE CELESTE CON SUAVIZANTE DE 5 LITROS | F11: =IFERROR(VLOOKUP(VENTAS[[#This Row],[CODIGO]],INVENTARIO[],3,FALSE),"NO EXISTE") -> LAVANDERIA | G11: =IFERROR(VLOOKUP(VENTAS[[#This Row],[CODIGO]],INVENTARIO[],8,FALSE),"NO EXISTE") -> 2500 | H11: =IFERROR(VLOOKUP(VENTAS[[#This Row],[CODIGO]],INVENTARIO[],7,FALSE),"NO EXISTE") -> 1490 | J11: =VENTAS[[#This Row],[PRECIO DE VENTA]]*VENTAS[[#This Row],[CANTIDAD]] -> 0 | K11: =VENTAS[[#This Row],[TOTAL DE LA VENTA]]-VENTAS[[#This Row],[COSTO UNITARIO]]*VENTAS[[#This Row],[CANTIDAD]] -> 0
A12: A006 | C12: =TEXT(VENTAS[[#This Row],[FECHA]],"[$-es-CL]mmmm") -> enero | D12: {=YEAR(IF(ISNUMBER(VENTAS[[#This Row],[FECHA]]),VENTAS[[#This Row],[FECHA]],FECHA.VALOR(VENTAS[[#This Row],[FECHA]])))} -> #NAME? | E12: =IFERROR(VLOOKUP(VENTAS[[#This Row],[CODIGO]],INVENTARIO[],2,FALSE),"NO EXISTE") -> DETERGENTE NARANJO CON SUAVIZANTE DE 5 LITROS | F12: =IFERROR(VLOOKUP(VENTAS[[#This Row],[CODIGO]],INVENTARIO[],3,FALSE),"NO EXISTE") -> LAVANDERIA | G12: =IFERROR(VLOOKUP(VENTAS[[#This Row],[CODIGO]],INVENTARIO[],8,FALSE),"NO EXISTE") -> 2500 | H12: =IFERROR(VLOOKUP(VENTAS[[#This Row],[CODIGO]],INVENTARIO[],7,FALSE),"NO EXISTE") -> 1490 | J12: =VENTAS[[#This Row],[PRECIO DE VENTA]]*VENTAS[[#This Row],[CANTIDAD]] -> 0 | K12: =VENTAS[[#This Row],[TOTAL DE LA VENTA]]-VENTAS[[#This Row],[COSTO UNITARIO]]*VENTAS[[#This Row],[CANTIDAD]] -> 0
A13: A007 | C13: =TEXT(VENTAS[[#This Row],[FECHA]],"[$-es-CL]mmmm") -> enero | D13: {=YEAR(IF(ISNUMBER(VENTAS[[#This Row],[FECHA]]),VENTAS[[#This Row],[FECHA]],FECHA.VALOR(VENTAS[[#This Row],[FECHA]])))} -> #NAME? | E13: =IFERROR(VLOOKUP(VENTAS[[#This Row],[CODIGO]],INVENTARIO[],2,FALSE),"NO EXISTE") -> DETERGENTE ROSADO CON SUAVIZANTE DE 5 LITROS | F13: =IFERROR(VLOOKUP(VENTAS[[#This Row],[CODIGO]],INVENTARIO[],3,FALSE),"NO EXISTE") -> LAVANDERIA | G13: =IFERROR(VLOOKUP(VENTAS[[#This Row],[CODIGO]],INVENTARIO[],8,FALSE),"NO EXISTE") -> 2500 | H13: =IFERROR(VLOOKUP(VENTAS[[#This Row],[CODIGO]],INVENTARIO[],7,FALSE),"NO EXISTE") -> 1490 | J13: =VENTAS[[#This Row],[PRECIO DE VENTA]]*VENTAS[[#This Row],[CANTIDAD]] -> 0 | K13: =VENTAS[[#This Row],[TOTAL DE LA VENTA]]-VENTAS[[#This Row],[COSTO UNITARIO]]*VENTAS[[#This Row],[CANTIDAD]] -> 0
A14: A008 | C14: =TEXT(VENTAS[[#This Row],[FECHA]],"[$-es-CL]mmmm") -> enero | D14: {=YEAR(IF(ISNUMBER(VENTAS[[#This Row],[FECHA]]),VENTAS[[#This Row],[FECHA]],FECHA.VALOR(VENTAS[[#This Row],[FECHA]])))} -> #NAME? | E14: =IFERROR(VLOOKUP(VENTAS[[#This Row],[CODIGO]],INVENTARIO[],2,FALSE),"NO EXISTE") -> DETERGENTE PREMIUM AROMA OMO DE 3 LITROS (PACK DE 4 UNID) | F14: =IFERROR(VLOOKUP(VENTAS[[#This Row],[CODIGO]],INVENTARIO[],3,FALSE),"NO EXISTE") -> LAVANDERIA | G14: =IFERROR(VLOOKUP(VENTAS[[#This Row],[CODIGO]],INVENTARIO[],8,FALSE),"NO EXISTE") -> 3000 | H14: =IFERROR(VLOOKUP(VENTAS[[#This Row],[CODIGO]],INVENTARIO[],7,FALSE),"NO EXISTE") -> 1350 | J14: =VENTAS[[#This Row],[PRECIO DE VENTA]]*VENTAS[[#This Row],[CANTIDAD]] -> 0 | K14: =VENTAS[[#This Row],[TOTAL DE LA VENTA]]-VENTAS[[#This Row],[COSTO UNITARIO]]*VENTAS[[#This Row],[CANTIDAD]] -> 0
A15: A009 | C15: =TEXT(VENTAS[[#This Row],[FECHA]],"[$-es-CL]mmmm") -> enero | D15: {=YEAR(IF(ISNUMBER(VENTAS[[#This Row],[FECHA]]),VENTAS[[#This Row],[FECHA]],FECHA.VALOR(VENTAS[[#This Row],[FECHA]])))} -> #NAME? | E15: =IFERROR(VLOOKUP(VENTAS[[#This Row],[CODIGO]],INVENTARIO[],2,FALSE),"NO EXISTE") -> DETERGENTE DE BEBÉ 3 LITROS | F15: =IFERROR(VLOOKUP(VENTAS[[#This Row],[CODIGO]],INVENTARIO[],3,FALSE),"NO EXISTE") -> LAVANDERIA | G15: =IFERROR(VLOOKUP(VENTAS[[#This Row],[CODIGO]],INVENTARIO[],8,FALSE),"NO EXISTE") -> 4000 | H15: =IFERROR(VLOOKUP(VENTAS[[#This Row],[CODIGO]],INVENTARIO[],7,FALSE),"NO EXISTE") -> 2450 | J15: =VENTAS[[#This Row],[PRECIO DE VENTA]]*VENTAS[[#This Row],[CANTIDAD]] -> 0 | K15: =VENTAS[[#This Row],[TOTAL DE LA VENTA]]-VENTAS[[#This Row],[COSTO UNITARIO]]*VENTAS[[#This Row],[CANTIDAD]] -> 0
A16: A010 | C16: =TEXT(VENTAS[[#This Row],[FECHA]],"[$-es-CL]mmmm") -> enero | D16: {=YEAR(IF(ISNUMBER(VENTAS[[#This Row],[FECHA]]),VENTAS[[#This Row],[FECHA]],FECHA.VALOR(VENTAS[[#This Row],[FECHA]])))} -> #NAME? | E16: =IFERROR(VLOOKUP(VENTAS[[#This Row],[CODIGO]],INVENTARIO[],2,FALSE),"NO EXISTE") -> DETERGENTE OMO PARA DILUIR 3 LITROS | F16: =IFERROR(VLOOKUP(VENTAS[[#This Row],[CODIGO]],INVENTARIO[],3,FALSE),"NO EXISTE") -> LAVANDERIA | G16: =IFERROR(VLOOKUP(VENTAS[[#This Row],[CODIGO]],INVENTARIO[],8,FALSE),"NO EXISTE") -> 4500 | H16: =IFERROR(VLOOKUP(VENTAS[[#This Row],[CODIGO]],INVENTARIO[],7,FALSE),"NO EXISTE") -> 3490 | J16: =VENTAS[[#This Row],[PRECIO DE VENTA]]*VENTAS[[#This Row],[CANTIDAD]] -> 0 | K16: =VENTAS[[#This Row],[TOTAL DE LA VENTA]]-VENTAS[[#This Row],[COSTO UNITARIO]]*VENTAS[[#This Row],[CANTIDAD]] -> 0
A17: A011 | C17: =TEXT(VENTAS[[#This Row],[FECHA]],"[$-es-CL]mmmm") -> enero | D17: {=YEAR(IF(ISNUMBER(VENTAS[[#This Row],[FECHA]]),VENTAS[[#This Row],[FECHA]],FECHA.VALOR(VENTAS[[#This Row],[FECHA]])))} -> #NAME? | E17: =IFERROR(VLOOKUP(VENTAS[[#This Row],[CODIGO]],INVENTARIO[],2,FALSE),"NO EXISTE") -> DETERGENTE OMO DE 400 ML | F17: =IFERROR(VLOOKUP(VENTAS[[#This Row],[CODIGO]],INVENTARIO[],3,FALSE),"NO EXISTE") -> LAVANDERIA | G17: =IFERROR(VLOOKUP(VENTAS[[#This Row],[CODIGO]],INVENTARIO[],8,FALSE),"NO EXISTE") -> 1000 | H17: =IFERROR(VLOOKUP(VENTAS[[#This Row],[CODIGO]],INVENTARIO[],7,FALSE),"NO EXISTE") -> 690 | J17: =VENTAS[[#This Row],[PRECIO DE VENTA]]*VENTAS[[#This Row],[CANTIDAD]] -> 0 | K17: =VENTAS[[#This Row],[TOTAL DE LA VENTA]]-VENTAS[[#This Row],[COSTO UNITARIO]]*VENTAS[[#This Row],[CANTIDAD]] -> 0
A18: A012 | C18: =TEXT(VENTAS[[#This Row],[FECHA]],"[$-es-CL]mmmm") -> enero | D18: {=YEAR(IF(ISNUMBER(VENTAS[[#This Row],[FECHA]]),VENTAS[[#This Row],[FECHA]],FECHA.VALOR(VENTAS[[#This Row],[FECHA]])))} -> #NAME? | E18: =IFERROR(VLOOKUP(VENTAS[[#This Row],[CODIGO]],INVENTARIO[],2,FALSE),"NO EXISTE") -> DETERGENTE OMO LIQUIDO BIDÓN 3 LITROS | F18: =IFERROR(VLOOKUP(VENTAS[[#This Row],[CODIGO]],INVENTARIO[],3,FALSE),"NO EXISTE") -> LAVANDERIA | G18: =IFERROR(VLOOKUP(VENTAS[[#This Row],[CODIGO]],INVENTARIO[],8,FALSE),"NO EXISTE") -> 0 | H18: =IFERROR(VLOOKUP(VENTAS[[#This Row],[CODIGO]],INVENTARIO[],7,FALSE),"NO EXISTE") -> 0 | J18: =VENTAS[[#This Row],[PRECIO DE VENTA]]*VENTAS[[#This Row],[CANTIDAD]] -> 0 | K18: =VENTAS[[#This Row],[TOTAL DE LA VENTA]]-VENTAS[[#This Row],[COSTO UNITARIO]]*VENTAS[[#This Row],[CANTIDAD]] -> 0
A19: A013 | C19: =TEXT(VENTAS[[#This Row],[FECHA]],"[$-es-CL]mmmm") -> enero | D19: {=YEAR(IF(ISNUMBER(VENTAS[[#This Row],[FECHA]]),VENTAS[[#This Row],[FECHA]],FECHA.VALOR(VENTAS[[#This Row],[FECHA]])))} -> #NAME? | E19: =IFERROR(VLOOKUP(VENTAS[[#This Row],[CODIGO]],INVENTARIO[],2,FALSE),"NO EXISTE") -> DETERGENTE BIO KLINNING AZUL | F19: =IFERROR(VLOOKUP(VENTAS[[#This Row],[CODIGO]],INVENTARIO[],3,FALSE),"NO EXISTE") -> LAVANDERIA | G19: =IFERROR(VLOOKUP(VENTAS[[#This Row],[CODIGO]],INVENTARIO[],8,FALSE),"NO EXISTE") -> 0 | H19: =IFERROR(VLOOKUP(VENTAS[[#This Row],[CODIGO]],INVENTARIO[],7,FALSE),"NO EXISTE") -> 950 | J19: =VENTAS[[#This Row],[PRECIO DE VENTA]]*VENTAS[[#This Row],[CANTIDAD]] -> 0 | K19: =VENTAS[[#This Row],[TOTAL DE LA VENTA]]-VENTAS[[#This Row],[COSTO UNITARIO]]*VENTAS[[#This Row],[CANTIDAD]] -> 0
A20: A014 | C20: =TEXT(VENTAS[[#This Row],[FECHA]],"[$-es-CL]mmmm") -> enero | D20: {=YEAR(IF(ISNUMBER(VENTAS[[#This Row],[FECHA]]),VENTAS[[#This Row],[FECHA]],FECHA.VALOR(VENTAS[[#This Row],[FECHA]])))} -> #NAME? | E20: =IFERROR(VLOOKUP(VENTAS[[#This Row],[CODIGO]],INVENTARIO[],2,FALSE),"NO EXISTE") -> DETERGENTE BIO KLINNING VERDE | F20: =IFERROR(VLOOKUP(VENTAS[[#This Row],[CODIGO]],INVENTARIO[],3,FALSE),"NO EXISTE") -> LAVANDERIA | G20: =IFERROR(VLOOKUP(VENTAS[[#This Row],[CODIGO]],INVENTARIO[],8,FALSE),"NO EXISTE") -> 0 | H20: =IFERROR(VLOOKUP(VENTAS[[#This Row],[CODIGO]],INVENTARIO[],7,FALSE),"NO EXISTE") -> 950 | J20: =VENTAS[[#This Row],[PRECIO DE VENTA]]*VENTAS[[#This Row],[CANTIDAD]] -> 0 | K20: =VENTAS[[#This Row],[TOTAL DE LA VENTA]]-VENTAS[[#This Row],[COSTO UNITARIO]]*VENTAS[[#This Row],[CANTIDAD]] -> 0
A21: A015 | C21: =TEXT(VENTAS[[#This Row],[FECHA]],"[$-es-CL]mmmm") -> enero | D21: {=YEAR(IF(ISNUMBER(VENTAS[[#This Row],[FECHA]]),VENTAS[[#This Row],[FECHA]],FECHA.VALOR(VENTAS[[#This Row],[FECHA]])))} -> #NAME? | E21: =IFERROR(VLOOKUP(VENTAS[[#This Row],[CODIGO]],INVENTARIO[],2,FALSE),"NO EXISTE") -> DETERGENTE SOFT LIQUIDO BIDÓN DE 3 LITROS | F21: =IFERROR(VLOOKUP(VENTAS[[#This Row],[CODIGO]],INVENTARIO[],3,FALSE),"NO EXISTE") -> LAVANDERIA | G21: =IFERROR(VLOOKUP(VENTAS[[#This Row],[CODIGO]],INVENTARIO[],8,FALSE),"NO EXISTE") -> 0 | H21: =IFERROR(VLOOKUP(VENTAS[[#This Row],[CODIGO]],INVENTARIO[],7,FALSE),"NO EXISTE") -> 0 | J21: =VENTAS[[#This Row],[PRECIO DE VENTA]]*VENTAS[[#This Row],[CANTIDAD]] -> 0 | K21: =VENTAS[[#This Row],[TOTAL DE LA VENTA]]-VENTAS[[#This Row],[COSTO UNITARIO]]*VENTAS[[#This Row],[CANTIDAD]] -> 0
A22: A016 | C22: =TEXT(VENTAS[[#This Row],[FECHA]],"[$-es-CL]mmmm") -> enero | D22: {=YEAR(IF(ISNUMBER(VENTAS[[#This Row],[FECHA]]),VENTAS[[#This Row],[FECHA]],FECHA.VALOR(VENTAS[[#This Row],[FECHA]])))} -> #NAME? | E22: =IFERROR(VLOOKUP(VENTAS[[#This Row],[CODIGO]],INVENTARIO[],2,FALSE),"NO EXISTE") -> DETERGENTE EN POLVO QUITA MANCHA ROSADO | F22: =IFERROR(VLOOKUP(VENTAS[[#This Row],[CODIGO]],INVENTARIO[],3,FALSE),"NO EXISTE") -> LAVANDERIA | G22: =IFERROR(VLOOKUP(VENTAS[[#This Row],[CODIGO]],INVENTARIO[],8,FALSE),"NO EXISTE") -> 1000 | H22: =IFERROR(VLOOKUP(VENTAS[[#This Row],[CODIGO]],INVENTARIO[],7,FALSE),"NO EXISTE") -> 490 | J22: =VENTAS[[#This Row],[PRECIO DE VENTA]]*VENTAS[[#This Row],[CANTIDAD]] -> 0 | K22: =VENTAS[[#This Row],[TOTAL DE LA VENTA]]-VENTAS[[#This Row],[COSTO UNITARIO]]*VENTAS[[#This Row],[CANTIDAD]] -> 0
... A63: A057 | C63: =TEXT(VENTAS[[#This Row],[FECHA]],"[$-es-CL]mmmm") -> enero | D63: {=YEAR(IF(ISNUMBER(VENTAS[[#This Row],[FECHA]]),VENTAS[[#This Row],[FECHA]],FECHA.VALOR(VENTAS[[#This Row],[FECHA]])))} -> #NAME? | E63: =IFERROR(VLOOKUP(VENTAS[[#This Row],[CODIGO]],INVENTARIO[],2,FALSE),"NO EXISTE") -> TOALLITAS DESINFECTANTE IGENIX | F63: =IFERROR(VLOOKUP(VENTAS[[#This Row],[CODIGO]],INVENTARIO[],3,FALSE),"NO EXISTE") -> SUPERFICIE | G63: =IFERROR(VLOOKUP(VENTAS[[#This Row],[CODIGO]],INVENTARIO[],8,FALSE),"NO EXISTE") -> 2500 | H63: =IFERROR(VLOOKUP(VENTAS[[#This Row],[CODIGO]],INVENTARIO[],7,FALSE),"NO EXISTE") -> 0 | J63: =VENTAS[[#This Row],[PRECIO DE VENTA]]*VENTAS[[#This Row],[CANTIDAD]] -> 0 | K63: =VENTAS[[#This Row],[TOTAL DE LA VENTA]]-VENTAS[[#This Row],[COSTO UNITARIO]]*VENTAS[[#This Row],[CANTIDAD]] -> 0
